{
    "country": "03",
    "class_1": "07",
    "내용분류": {
        "감정": [
            "두려움"
        ],
        "대화형태": [
            "설명"
        ],
        "행동": [
            "반응"
        ],
        "인물관계": [
            "원수"
        ],
        "캐릭터": [
            "왕족/귀족"
        ],
        "직업/신분": [
            "관리"
        ],
        "장르": [
            "설화"
        ],
        "사건/모티프": [
            "기적"
        ],
        "공간": [
            "일본"
        ]
    },
    "주제어": [
        "판관대",
        "살해",
        "소문",
        "확인",
        "적"
    ],
    "주제문": "판관대가 살해되었다는 소문이 퍼졌지만, 그는 상처 하나 없이 멀쩡하게 살아 있었다."
}