{
    "country": "01",
    "class_1": "02",
    "내용분류": {
        "감정": [
            "놀람"
        ],
        "대화형태": [
            "해당없음"
        ],
        "행동": [
            "반응"
        ],
        "인물관계": [
            "군신"
        ],
        "캐릭터": [
            "여성",
            "왕족/귀족"
        ],
        "직업/신분": [
            "왕",
            "신하"
        ],
        "장르": [
            "가문소설"
        ],
        "사건/모티프": [
            "보상/징벌"
        ],
        "공간": [
            "궁"
        ]
    },
    "주제어": [
        "영릉",
        "제사",
        "향초",
        "희생제물",
        "공주"
    ],
    "주제문": "임금은 영릉후에게 제사 때 필요한 향초와 희생제물을 가져오게 하여 공주의 묘당에 제사지내도록 명령하셨다."
}