{
    "country": "01",
    "class_1": "02",
    "내용분류": {
        "감정": [
            "의심"
        ],
        "대화형태": [
            "질문",
            "답변"
        ],
        "행동": [
            "반응",
            "갈등"
        ],
        "인물관계": [
            "부모와자식"
        ],
        "캐릭터": [
            "왕족/귀족",
            "서생"
        ],
        "직업/신분": [
            "신하"
        ],
        "장르": [
            "가문소설"
        ],
        "사건/모티프": [
            "보상/징벌"
        ],
        "공간": [
            "궁"
        ]
    },
    "주제어": [
        "진공",
        "진실",
        "공자",
        "간악한",
        "훈계"
    ],
    "주제문": "진공은 셋째 공자가 현에게 무엇을 지시받았는지 의혹하며 진실을 꿰뚫어보고 훈계할 것을 밝힌다."
}