{
    "id": "03_1543",
    "type": "novel",
    "title": "예술이 된 여자",
    "genre": [
        "드라마",
        "멜로/로맨스"
    ],
    "year": 2003,
    "theme": "유혹",
    "concept": "C002의 진주 귀걸이를 한 소녀라는 그림에 대한 비화를 다룬다.",
    "structure": "스토리헬퍼 15단계",
    "motif": "고귀한 창녀",
    "main_character": "하녀(시녀)",
    "conflict": "C002의 그림 주인공이 돼버린 C001의 비운의 운명에 대한 이야기이다.",
    "characters": [
        "C001",
        "C002",
        "C003",
        "C004",
        "C005",
        "C006",
        "C007",
        "C008"
    ],
    "units": [
        {
            "id": "03_1543_01",
            "next_id": "03_1543_02",
            "characters": [
                "C001",
                "C005"
            ],
            "stage": "Main Character",
            "storyline": "처음으로 C002의 집에 발을 들여놓는다.",
            "unit_motif": "이계방문",
            "causality": "Misdirection(잘못된 선택)",
            "story_scripts": [
                {
                    "type": "narrative",
                    "location": "C001 집",
                    "character": [
                        "C001"
                    ],
                    "act": "말하다",
                    "content": "어머니가 C001에게 음식을 싸 주신다."
                },
                {
                    "type": "narrative",
                    "location": "C001 집",
                    "character": [
                        "C001"
                    ],
                    "act": "말하다",
                    "emotion": "걱정",
                    "content": "어머니가 주인집 미사에 참여하지 말라고 주의를 준다."
                },
                {
                    "type": "narrative",
                    "location": "거리",
                    "character": [
                        "C001"
                    ],
                    "act": "간다/이동한다",
                    "content": "C001가 자신이 일하게 될 집을 찾아간다."
                },
                {
                    "type": "narrative",
                    "location": "거리",
                    "character": [
                        "C001"
                    ],
                    "act": "간다/이동한다",
                    "emotion": "긴장되다",
                    "content": "C001가 갈림길에서 잠시 망설인다."
                },
                {
                    "type": "narrative",
                    "location": "거리",
                    "character": [
                        "C001"
                    ],
                    "act": "간다/이동한다",
                    "content": "C001가 이내 발걸음을 옮긴다."
                },
                {
                    "type": "narrative",
                    "location": "집앞",
                    "character": [
                        "C001"
                    ],
                    "act": "묻는다",
                    "content": "C002의 딸들이 집 앞에서 놀고 있다."
                },
                {
                    "type": "narrative",
                    "location": "집앞",
                    "character": [
                        "C001"
                    ],
                    "act": "묻는다",
                    "content": "C001는 여기가 C002의 집이 맞는지 물어본다."
                },
                {
                    "type": "narrative",
                    "location": "집앞",
                    "character": [
                        "C001"
                    ],
                    "act": "묻는다",
                    "content": "C007는 C001에게 적대적이다."
                },
                {
                    "type": "narrative",
                    "location": "집",
                    "character": [
                        "C001",
                        "C005"
                    ],
                    "act": "말하다",
                    "content": "C001가 집으로 들어간다."
                },
                {
                    "type": "narrative",
                    "location": "집",
                    "character": [
                        "C001",
                        "C005"
                    ],
                    "act": "말하다",
                    "content": "C005는 무뚝뚝하게 C001가 해야 할 일을 알려준다."
                }
            ]
        },
        {
            "id": "03_1543_02",
            "prev_id": "03_1543_01",
            "next_id": "03_1543_03",
            "characters": [
                "C001",
                "C005"
            ],
            "stage": "Main Character",
            "storyline": "C001가 집에서 해야 할 일들을 알아간다.",
            "unit_motif": "이계방문",
            "causality": "Misdirection(잘못된 선택)",
            "story_scripts": [
                {
                    "type": "narrative",
                    "location": "집",
                    "character": [
                        "C001",
                        "C005"
                    ],
                    "act": "말하다",
                    "emotion": "귀찮다",
                    "content": "C005가 C001의 거처를 안내한다."
                },
                {
                    "type": "narrative",
                    "location": "집",
                    "character": [
                        "C001",
                        "C005"
                    ],
                    "act": "간다/이동한다",
                    "content": "C005가 집안 곳곳을 돌아다니며 설명한다."
                },
                {
                    "type": "narrative",
                    "location": "집",
                    "character": [
                        "C001",
                        "C005"
                    ],
                    "act": "간다/이동한다",
                    "content": "C001가 화실에 들어가려 한다."
                },
                {
                    "type": "narrative",
                    "location": "집",
                    "character": [
                        "C001",
                        "C005"
                    ],
                    "act": "간다/이동한다",
                    "content": "C005는 이를 말린다."
                },
                {
                    "type": "narrative",
                    "location": "방",
                    "character": [
                        "C001",
                        "C005"
                    ],
                    "act": "간다/이동한다",
                    "content": "C001가 자신이 머물 곳을 살펴본다."
                },
                {
                    "type": "narrative",
                    "location": "방",
                    "character": [
                        "C001",
                        "C005"
                    ],
                    "act": "간다/이동한다",
                    "content": "지하 창고 안이 그녀가 잠잘 곳이다."
                },
                {
                    "type": "narrative",
                    "location": "방",
                    "character": [
                        "C001"
                    ],
                    "act": "자다/잠들다",
                    "content": "C001가 침대에 눕는다."
                },
                {
                    "type": "narrative",
                    "location": "방",
                    "character": [
                        "C001"
                    ],
                    "act": "자다/잠들다",
                    "emotion": "불편하다",
                    "content": "낯선 곳에서 맞이하는 잠자리가 편치 않다."
                },
                {
                    "type": "narrative",
                    "location": "방",
                    "character": [
                        "C001"
                    ],
                    "act": "자다/잠들다",
                    "content": "C001는 쉽게 잠들지 못한다."
                },
                {
                    "type": "narrative",
                    "location": "방",
                    "character": [
                        "C001"
                    ],
                    "act": "자다/잠들다",
                    "content": "C001가 한 숨을 내쉰다."
                }
            ]
        },
        {
            "id": "03_1543_03",
            "prev_id": "03_1543_02",
            "next_id": "03_1543_04",
            "characters": [
                "C001",
                "C008"
            ],
            "stage": "Setting-up",
            "storyline": "C001가 일을 시작한다.",
            "unit_motif": "낯선 곳으로의 이주",
            "causality": "Suggestion(제안)",
            "story_scripts": [
                {
                    "type": "narrative",
                    "location": "부엌",
                    "character": [
                        "C001"
                    ],
                    "act": "간다/이동한다",
                    "content": "C001가 물을 길어온다."
                },
                {
                    "type": "narrative",
                    "location": "부엌",
                    "character": [
                        "C001"
                    ],
                    "act": "간다/이동한다",
                    "content": "C001가 빨래를 삶는다."
                },
                {
                    "type": "narrative",
                    "location": "부엌",
                    "character": [
                        "C001"
                    ],
                    "act": "간다/이동한다",
                    "emotion": "불편하다",
                    "content": "C001는 일이 익숙지 않다."
                },
                {
                    "type": "narrative",
                    "location": "부엌",
                    "character": [
                        "C001"
                    ],
                    "act": "간다/이동한다",
                    "content": "C001가 손을 다친다."
                },
                {
                    "type": "narrative",
                    "location": "마당",
                    "character": [
                        "C001",
                        "C008"
                    ],
                    "act": "만나다",
                    "content": "C001가 C008와 처음 만난다."
                },
                {
                    "type": "narrative",
                    "location": "마당",
                    "character": [
                        "C001",
                        "C008"
                    ],
                    "act": "만나다",
                    "content": "C008는 냉정하게 C001를 대한다."
                },
                {
                    "type": "narrative",
                    "location": "마당",
                    "character": [
                        "C001",
                        "C008"
                    ],
                    "act": "만나다",
                    "content": "C008가 C001를 화실로 안내한다."
                },
                {
                    "type": "narrative",
                    "location": "마당",
                    "character": [
                        "C001",
                        "C008"
                    ],
                    "act": "만나다",
                    "content": "C008는 만삭이다."
                },
                {
                    "type": "narrative",
                    "location": "마당",
                    "character": [
                        "C001",
                        "C008"
                    ],
                    "act": "만나다",
                    "emotion": "짜증나다",
                    "content": "C008는 C001에게 신경질적이다."
                },
                {
                    "type": "narrative",
                    "location": "마당",
                    "character": [
                        "C001",
                        "C008"
                    ],
                    "act": "만나다",
                    "content": "C008는 C001를 화실에 들여보낸다."
                }
            ]
        },
        {
            "id": "03_1543_04",
            "prev_id": "03_1543_03",
            "next_id": "03_1543_05",
            "characters": [
                "C001",
                "C008"
            ],
            "stage": "Setting-up",
            "storyline": "화실 청소까지가 그녀의 몫이다.",
            "unit_motif": "낯선 곳으로의 이주",
            "causality": "Suggestion(제안)",
            "story_scripts": [
                {
                    "type": "narrative",
                    "location": "화실",
                    "character": [
                        "C001",
                        "C008"
                    ],
                    "act": "공개하다/드러내다",
                    "emotion": "황홀하다",
                    "content": "C001가 화실로 들어간다."
                },
                {
                    "type": "narrative",
                    "location": "화실",
                    "character": [
                        "C001",
                        "C008"
                    ],
                    "act": "공개하다/드러내다",
                    "content": "C001는 처음 보는 광경에 마음을 빼앗긴다."
                },
                {
                    "type": "narrative",
                    "location": "화실",
                    "character": [
                        "C001",
                        "C008"
                    ],
                    "act": "공개하다/드러내다",
                    "content": "C008는 C001의 모습을 신경 쓰지 않는다."
                },
                {
                    "type": "narrative",
                    "location": "화실",
                    "character": [
                        "C001",
                        "C008"
                    ],
                    "act": "공개하다/드러내다",
                    "emotion": "걱정",
                    "content": "C008는 아무것도 건드리지 말라고 이른다."
                },
                {
                    "type": "narrative",
                    "location": "화실",
                    "character": [
                        "C001",
                        "C008"
                    ],
                    "act": "공개하다/드러내다",
                    "content": "C001는 알겠다고 대답한다."
                },
                {
                    "type": "narrative",
                    "location": "화실",
                    "character": [
                        "C001",
                        "C008"
                    ],
                    "act": "공개하다/드러내다",
                    "content": "C001가 청소를 위해 덧 문을 연다."
                },
                {
                    "type": "narrative",
                    "location": "화실",
                    "character": [
                        "C001"
                    ],
                    "act": "수색하다",
                    "content": "C008는 문을 닫고 나간다."
                },
                {
                    "type": "narrative",
                    "location": "화실",
                    "character": [
                        "C001"
                    ],
                    "act": "수색하다",
                    "content": "C001가 조심조심 청소를 시작한다."
                },
                {
                    "type": "narrative",
                    "location": "화실",
                    "character": [
                        "C001"
                    ],
                    "act": "수색하다",
                    "content": "C001가 물건을 건드리지 않고 청소를 한다."
                },
                {
                    "type": "narrative",
                    "location": "화실",
                    "character": [
                        "C001"
                    ],
                    "act": "수색하다",
                    "content": "C001가 청소하면서도 황홀해한다."
                }
            ]
        },
        {
            "id": "03_1543_05",
            "prev_id": "03_1543_04",
            "next_id": "03_1543_06",
            "characters": [
                "C001",
                "C002",
                "C005"
            ],
            "stage": "Doubts & Debate",
            "storyline": "C001가 C002와 처음으로 만나고, C008의 출산을 돕는다.",
            "unit_motif": "악마적인 예술가",
            "causality": "Crisis of the heart(지극한 슬픔)",
            "story_scripts": [
                {
                    "type": "narrative",
                    "location": "방",
                    "character": [
                        "C001",
                        "C002"
                    ],
                    "act": "만나다",
                    "content": "C001가 청소를 하고 있다."
                },
                {
                    "type": "narrative",
                    "location": "방",
                    "character": [
                        "C001",
                        "C002"
                    ],
                    "act": "만나다",
                    "content": "C002가 지나간다."
                },
                {
                    "type": "narrative",
                    "location": "방",
                    "character": [
                        "C001",
                        "C002"
                    ],
                    "act": "만나다",
                    "emotion": "당황하다",
                    "content": "C001가 말없이 인사를 한다."
                },
                {
                    "type": "narrative",
                    "location": "방",
                    "character": [
                        "C001",
                        "C002"
                    ],
                    "act": "만나다",
                    "content": "C001가 청소를 계속한다."
                },
                {
                    "type": "narrative",
                    "location": "방",
                    "character": [
                        "C001"
                    ],
                    "act": "만나다",
                    "content": "밤이 되어 C001가 잠에 든다."
                },
                {
                    "type": "narrative",
                    "location": "방",
                    "character": [
                        "C001"
                    ],
                    "act": "만나다",
                    "content": "어디선가 비명 소리가 들린다."
                },
                {
                    "type": "narrative",
                    "location": "방",
                    "character": [
                        "C001"
                    ],
                    "act": "간다/이동한다",
                    "emotion": "놀라다",
                    "content": "C001가 자다가 비명 소리에 깬다."
                },
                {
                    "type": "narrative",
                    "location": "방",
                    "character": [
                        "C001",
                        "C005"
                    ],
                    "act": "간다/이동한다",
                    "content": "C008의 산고가 시작되었다."
                },
                {
                    "type": "narrative",
                    "location": "방",
                    "character": [
                        "C001",
                        "C005"
                    ],
                    "act": "간다/이동한다",
                    "content": "C001가 C005와 함께 출산 준비를 돕는다."
                },
                {
                    "type": "narrative",
                    "location": "안방",
                    "character": [
                        "C001",
                        "C005"
                    ],
                    "act": "간다/이동한다",
                    "content": "C001가 태어난 아이를 받는다."
                }
            ]
        },
        {
            "id": "03_1543_06",
            "prev_id": "03_1543_05",
            "next_id": "03_1543_07",
            "characters": [
                "C001",
                "C005",
                "C006",
                "C004"
            ],
            "stage": "Doubts & Debate",
            "storyline": "C001는 C004에게 편지를 전하는 심부름을 하며 C002의 그림을 보게 된다.",
            "unit_motif": "악마적인 예술가",
            "causality": "Crisis of the heart(지극한 슬픔)",
            "story_scripts": [
                {
                    "type": "narrative",
                    "location": "안방",
                    "character": [
                        "C001",
                        "C005"
                    ],
                    "act": "간다/이동한다",
                    "content": "C001가 태어난 아기를 빤히 바라본다."
                },
                {
                    "type": "narrative",
                    "location": "안방",
                    "character": [
                        "C001",
                        "C006"
                    ],
                    "act": "간다/이동한다",
                    "content": "C001에게 C006가 심부름을 시킨다."
                },
                {
                    "type": "narrative",
                    "location": "안방",
                    "character": [
                        "C001",
                        "C006"
                    ],
                    "act": "간다/이동한다",
                    "content": "C006가 C001에게 편지를 하나 건네준다."
                },
                {
                    "type": "narrative",
                    "location": "안방",
                    "character": [
                        "C001",
                        "C006"
                    ],
                    "act": "간다/이동한다",
                    "emotion": "단호하다",
                    "content": "심부름은 C002의 후원자인 C004에게 보내는 편지를 전해주라는 것이다."
                },
                {
                    "type": "narrative",
                    "location": "거리",
                    "character": [
                        "C001"
                    ],
                    "act": "간다/이동한다",
                    "content": "C001가 편지를 가지고 C004에게 간다."
                },
                {
                    "type": "narrative",
                    "location": "거리",
                    "character": [
                        "C001"
                    ],
                    "act": "간다/이동한다",
                    "content": "C001가 배를 타고 간다."
                },
                {
                    "type": "narrative",
                    "location": "C004 집",
                    "character": [
                        "C001",
                        "C004"
                    ],
                    "act": "위협하다/협박하다",
                    "content": "C001가 C004에게 편지를 건넨다."
                },
                {
                    "type": "narrative",
                    "location": "C004 집",
                    "character": [
                        "C001",
                        "C004"
                    ],
                    "act": "위협하다/협박하다",
                    "emotion": "거부감",
                    "content": "C004은 C001를 음탕한 눈빛으로 바라본다."
                },
                {
                    "type": "narrative",
                    "location": "C004 집",
                    "character": [
                        "C001",
                        "C004"
                    ],
                    "act": "위협하다/협박하다",
                    "content": "C004은 C002가 그린 그림을 보여준다."
                },
                {
                    "type": "narrative",
                    "location": "C004 집",
                    "character": [
                        "C001",
                        "C004"
                    ],
                    "act": "위협하다/협박하다",
                    "content": "C001는 C002의 그림을 본다."
                }
            ]
        },
        {
            "id": "03_1543_07",
            "prev_id": "03_1543_06",
            "next_id": "03_1543_08",
            "characters": [
                "C001",
                "C005"
            ],
            "stage": "Making a Choice",
            "storyline": "C005가 C001에게 그림 속의 여인의 흉을 본다.",
            "unit_motif": "지리적 고립",
            "causality": "Showdown(결전)",
            "story_scripts": [
                {
                    "type": "narrative",
                    "location": "부엌",
                    "character": [
                        "C001",
                        "C005"
                    ],
                    "act": "담소를 나누다",
                    "content": "C005가 그림에 대한 이야기를 꺼낸다."
                },
                {
                    "type": "narrative",
                    "location": "부엌",
                    "character": [
                        "C001",
                        "C005"
                    ],
                    "act": "담소를 나누다",
                    "emotion": "경멸하다",
                    "content": "C005는 그림 속의 여인 흉을 본다."
                },
                {
                    "type": "narrative",
                    "location": "부엌",
                    "character": [
                        "C001",
                        "C005"
                    ],
                    "act": "담소를 나누다",
                    "content": "C001는 영문을 모르고 듣는다."
                },
                {
                    "type": "narrative",
                    "location": "부엌",
                    "character": [
                        "C001",
                        "C005"
                    ],
                    "act": "담소를 나누다",
                    "content": "C005가 그 하녀에 대한 소문을 말한다."
                },
                {
                    "type": "narrative",
                    "location": "부엌",
                    "character": [
                        "C001",
                        "C005"
                    ],
                    "act": "담소를 나누다",
                    "content": "C005는 그 하녀가 C004의 아이를 가지고 쫓겨났다고 말한다."
                },
                {
                    "type": "narrative",
                    "location": "부엌",
                    "character": [
                        "C001",
                        "C005"
                    ],
                    "act": "담소를 나누다",
                    "emotion": "담담하다",
                    "content": "C001는 말없이 C005의 말을 듣는다."
                },
                {
                    "type": "narrative",
                    "location": "부엌",
                    "character": [
                        "C001",
                        "C005"
                    ],
                    "act": "간다/이동한다",
                    "content": "C005와 C001는 바쁘게 파티 준비를 한다."
                },
                {
                    "type": "narrative",
                    "location": "부엌",
                    "character": [
                        "C001",
                        "C005"
                    ],
                    "act": "간다/이동한다",
                    "content": "아기의 탄생을 축하하는 파티를 열려고 한다."
                },
                {
                    "type": "narrative",
                    "location": "부엌",
                    "character": [
                        "C001",
                        "C005"
                    ],
                    "act": "간다/이동한다",
                    "content": "파티에 필요한 것들이 집으로 온다."
                },
                {
                    "type": "narrative",
                    "location": "부엌",
                    "character": [
                        "C001",
                        "C005"
                    ],
                    "act": "간다/이동한다",
                    "content": "수많은 사람들이 집을 오고 간다."
                }
            ]
        },
        {
            "id": "03_1543_08",
            "prev_id": "03_1543_07",
            "next_id": "03_1543_09",
            "characters": [
                "C001",
                "C003"
            ],
            "stage": "Making a Choice",
            "storyline": "C002에게 새아기가 태어나 파티 준비를 한다.",
            "unit_motif": "지리적 고립",
            "causality": "Approaching the threshold(임계점 도달)",
            "story_scripts": [
                {
                    "type": "narrative",
                    "location": "집",
                    "character": [
                        "C001"
                    ],
                    "act": "간다/이동한다",
                    "content": "C001도 파티 준비를 위해 청소를 한다."
                },
                {
                    "type": "narrative",
                    "location": "집",
                    "character": [
                        "C001"
                    ],
                    "act": "간다/이동한다",
                    "emotion": "지겹다",
                    "content": "C001는 빨래를 하느라 여념이 없다."
                },
                {
                    "type": "narrative",
                    "location": "집",
                    "character": [
                        "C001",
                        "C003"
                    ],
                    "act": "간다/이동한다",
                    "content": "C003가 고기를 배달하러 온다."
                },
                {
                    "type": "narrative",
                    "location": "집",
                    "character": [
                        "C001",
                        "C003"
                    ],
                    "act": "간다/이동한다",
                    "content": "C003가 C001에게 다가가 말을 건다."
                },
                {
                    "type": "narrative",
                    "location": "집",
                    "character": [
                        "C001",
                        "C003"
                    ],
                    "act": "간다/이동한다",
                    "content": "C001는 C003를 쌀쌀맞게 대한다."
                },
                {
                    "type": "narrative",
                    "location": "집",
                    "act": "간다/이동한다",
                    "emotion": "거부감",
                    "content": "손님들은 파티를 즐기기 위해 배를 타고 도착한다."
                },
                {
                    "type": "narrative",
                    "location": "집",
                    "act": "간다/이동한다",
                    "content": "집 앞은 손님들로 붐빈다."
                },
                {
                    "type": "narrative",
                    "location": "부엌",
                    "character": [
                        "C001"
                    ],
                    "act": "간다/이동한다",
                    "content": "많은 손님들이 파티를 즐기고 있다."
                },
                {
                    "type": "narrative",
                    "location": "부엌",
                    "character": [
                        "C001"
                    ],
                    "act": "간다/이동한다",
                    "content": "C001는 파티를 즐기는 사람들을 바라본다."
                },
                {
                    "type": "narrative",
                    "location": "부엌",
                    "character": [
                        "C001"
                    ],
                    "act": "간다/이동한다",
                    "content": "C001는 말없이 한참을 본다."
                }
            ]
        },
        {
            "id": "03_1543_09",
            "prev_id": "03_1543_08",
            "next_id": "03_1543_10",
            "characters": [
                "C002",
                "C006",
                "C008",
                "C005",
                "C001"
            ],
            "stage": "Another Story",
            "storyline": "C001가 C002 집에서의 생활을 계속 해나간다.",
            "unit_motif": "가문의 여주인",
            "causality": "Touch of the death(애석한 죽음)",
            "story_scripts": [
                {
                    "type": "narrative",
                    "location": "집",
                    "character": [
                        "C002",
                        "C006",
                        "C008"
                    ],
                    "act": "추켜세우다",
                    "emotion": "감동하다",
                    "content": "C006가 환영사를 한다."
                },
                {
                    "type": "narrative",
                    "location": "집",
                    "character": [
                        "C002",
                        "C006",
                        "C008"
                    ],
                    "act": "추켜세우다",
                    "content": "동시에 새 그림을 발표한다."
                },
                {
                    "type": "narrative",
                    "location": "집",
                    "character": [
                        "C002",
                        "C006",
                        "C008"
                    ],
                    "act": "추켜세우다",
                    "content": "C004이 그림을 감상한다."
                },
                {
                    "type": "narrative",
                    "location": "집",
                    "character": [
                        "C002",
                        "C006",
                        "C008"
                    ],
                    "act": "추켜세우다",
                    "emotion": "궁금하다",
                    "content": "C008는 C004의 생각을 묻는다."
                },
                {
                    "type": "narrative",
                    "location": "집",
                    "character": [
                        "C002",
                        "C006",
                        "C008"
                    ],
                    "act": "추켜세우다",
                    "content": "C004은 훌륭하다고 대답한다."
                },
                {
                    "type": "narrative",
                    "location": "거리",
                    "character": [
                        "C005"
                    ],
                    "act": "간다/이동한다",
                    "content": "C005는 쓰레기를 버리고 있다."
                },
                {
                    "type": "narrative",
                    "location": "화실",
                    "character": [
                        "C001"
                    ],
                    "act": "묻는다",
                    "content": "C001가 청소를 하고 있다."
                },
                {
                    "type": "narrative",
                    "location": "화실",
                    "character": [
                        "C001"
                    ],
                    "act": "묻는다",
                    "content": "창문의 먼지를 확인하고 있다."
                },
                {
                    "type": "narrative",
                    "location": "화실",
                    "character": [
                        "C001"
                    ],
                    "act": "묻는다",
                    "content": "C001는 C008에게 창문을 닦아도 되는지 묻는다."
                },
                {
                    "type": "narrative",
                    "location": "화실",
                    "character": [
                        "C001"
                    ],
                    "act": "묻는다",
                    "content": "C008는 닦으라고 말한다."
                }
            ]
        },
        {
            "id": "03_1543_10",
            "prev_id": "03_1543_09",
            "next_id": "03_1543_11",
            "characters": [
                "C001",
                "C002",
                "C003"
            ],
            "stage": "Trailer Moments",
            "storyline": "C002는 C001를 그리기로 결심한다.",
            "unit_motif": "첫눈에 반한 사랑",
            "causality": "Touch of the death(애석한 죽음)",
            "story_scripts": [
                {
                    "type": "narrative",
                    "location": "화실",
                    "character": [
                        "C001",
                        "C002"
                    ],
                    "act": "명령하다",
                    "content": "C001가 창문을 닦는다."
                },
                {
                    "type": "narrative",
                    "location": "화실",
                    "character": [
                        "C001",
                        "C002"
                    ],
                    "act": "명령하다",
                    "content": "C002가 그런 그녀의 모습을 바라본다."
                },
                {
                    "type": "narrative",
                    "location": "화실",
                    "character": [
                        "C001",
                        "C002"
                    ],
                    "act": "명령하다",
                    "emotion": "난감하다",
                    "content": "그가 화실 안으로 걸어 들어온다."
                },
                {
                    "type": "narrative",
                    "location": "화실",
                    "character": [
                        "C001",
                        "C002"
                    ],
                    "act": "명령하다",
                    "content": "C001가 C002에게 인사한다."
                },
                {
                    "type": "narrative",
                    "location": "화실",
                    "character": [
                        "C001",
                        "C002"
                    ],
                    "act": "명령하다",
                    "content": "C001는 조심스럽게 청소를 한다."
                },
                {
                    "type": "narrative",
                    "location": "화실",
                    "character": [
                        "C001",
                        "C002"
                    ],
                    "act": "명령하다",
                    "emotion": "궁금하다",
                    "content": "C002가 C001를 빤히 바라본다."
                },
                {
                    "type": "narrative",
                    "location": "화실",
                    "character": [
                        "C001",
                        "C002"
                    ],
                    "act": "명령하다",
                    "content": "C002가 C001에게 포즈를 주문한다."
                },
                {
                    "type": "narrative",
                    "location": "화실",
                    "character": [
                        "C001",
                        "C002"
                    ],
                    "act": "간다/이동한다",
                    "content": "C001에게 포즈를 주문한 C002는 그대로 방을 나간다."
                },
                {
                    "type": "narrative",
                    "location": "거리",
                    "character": [
                        "C001",
                        "C003"
                    ],
                    "act": "만나다",
                    "content": "C001가 교회에 간다."
                },
                {
                    "type": "narrative",
                    "location": "거리",
                    "character": [
                        "C001",
                        "C003"
                    ],
                    "act": "만나다",
                    "content": "교회에 C003가 들어온다."
                }
            ]
        },
        {
            "id": "03_1543_11",
            "prev_id": "03_1543_10",
            "next_id": "03_1543_12",
            "characters": [
                "C001",
                "C003",
                "C006",
                "C002"
            ],
            "stage": "Trailer Moments",
            "storyline": "C003는 C001에게 구애를 한다.",
            "unit_motif": "첫눈에 반한 사랑",
            "causality": "Touch of the death(애석한 죽음)",
            "story_scripts": [
                {
                    "type": "narrative",
                    "location": "거리",
                    "character": [
                        "C001",
                        "C003"
                    ],
                    "act": "만나다",
                    "emotion": "놀라다",
                    "content": "C001는 놀란다."
                },
                {
                    "type": "narrative",
                    "location": "교회",
                    "character": [
                        "C001",
                        "C003"
                    ],
                    "act": "만나다",
                    "content": "예배가 끝난다."
                },
                {
                    "type": "narrative",
                    "location": "교회 앞",
                    "character": [
                        "C001",
                        "C003"
                    ],
                    "act": "만나다",
                    "content": "C001가 부모님에게 C003를 소개한다."
                },
                {
                    "type": "narrative",
                    "location": "교회 앞",
                    "character": [
                        "C001",
                        "C003"
                    ],
                    "act": "만나다",
                    "content": "어머니는 자리를 피한다."
                },
                {
                    "type": "narrative",
                    "location": "거리",
                    "character": [
                        "C001",
                        "C003"
                    ],
                    "act": "놀다",
                    "content": "C001와 C003가 함께 거리를 걷는다."
                },
                {
                    "type": "narrative",
                    "location": "집",
                    "character": [
                        "C001",
                        "C006"
                    ],
                    "act": "말하다",
                    "content": "C006가 C001에게 말을 건다."
                },
                {
                    "type": "narrative",
                    "location": "집",
                    "character": [
                        "C001",
                        "C006"
                    ],
                    "act": "말하다",
                    "content": "C006가 C002가 다시 그림을 시작했다고 C001에게 알린다."
                },
                {
                    "type": "narrative",
                    "location": "집",
                    "character": [
                        "C001",
                        "C006"
                    ],
                    "act": "말하다",
                    "emotion": "의심스럽다",
                    "content": "C006가 날카로운 눈빛으로 C001를 바라본다."
                },
                {
                    "type": "narrative",
                    "location": "화실",
                    "character": [
                        "C002"
                    ],
                    "act": "만들다",
                    "content": "C002가 모델을 세워둔다."
                },
                {
                    "type": "narrative",
                    "location": "화실",
                    "character": [
                        "C002"
                    ],
                    "act": "만들다",
                    "content": "C002가 그림을 그린다."
                }
            ]
        },
        {
            "id": "03_1543_12",
            "prev_id": "03_1543_11",
            "next_id": "03_1543_13",
            "characters": [
                "C001",
                "C002"
            ],
            "stage": "Ups & Downs",
            "storyline": "C001는 점점 더 예술의 세계에 심취한다.",
            "unit_motif": "계급을 초월한 사랑",
            "causality": "Temptation(유혹)",
            "story_scripts": [
                {
                    "type": "narrative",
                    "location": "화실",
                    "character": [
                        "C001",
                        "C002"
                    ],
                    "act": "찾는다",
                    "content": "C001가 청소를 하러 들어온다."
                },
                {
                    "type": "narrative",
                    "location": "화실",
                    "character": [
                        "C001",
                        "C002"
                    ],
                    "act": "찾는다",
                    "emotion": "궁금하다",
                    "content": "C001는 짐꾼들이 물체를 옮기는 것을 바라본다."
                },
                {
                    "type": "narrative",
                    "location": "화실",
                    "character": [
                        "C001",
                        "C002"
                    ],
                    "act": "찾는다",
                    "content": "짐꾼들이 물체를 다 옮기고 나간다."
                },
                {
                    "type": "narrative",
                    "location": "화실",
                    "character": [
                        "C001",
                        "C002"
                    ],
                    "act": "찾는다",
                    "content": "C001가 그 물체를 쳐다본다."
                },
                {
                    "type": "narrative",
                    "location": "화실",
                    "character": [
                        "C001",
                        "C002"
                    ],
                    "act": "찾는다",
                    "emotion": "설레다",
                    "content": "C002가 그런 C001를 바라본다."
                },
                {
                    "type": "narrative",
                    "location": "화실",
                    "character": [
                        "C001",
                        "C002"
                    ],
                    "act": "말하다",
                    "content": "C002가 C001에게 카메라 옵스큐라를 보는 법을 알려준다."
                },
                {
                    "type": "narrative",
                    "location": "집앞",
                    "act": "위협하다/협박하다",
                    "content": "C001가 그릇을 닦는다."
                },
                {
                    "type": "narrative",
                    "location": "집앞",
                    "act": "위협하다/협박하다",
                    "content": "C001가 그릇이 만들어내는 빛을 신기하게 쳐다본다."
                },
                {
                    "type": "narrative",
                    "location": "집앞",
                    "act": "위협하다/협박하다",
                    "content": "딸들이 집 앞에서 뛰어논다."
                },
                {
                    "type": "narrative",
                    "location": "집앞",
                    "act": "위협하다/협박하다",
                    "content": "C002가 시끄러운 딸들에게 신경질을 낸다."
                }
            ]
        },
        {
            "id": "03_1543_13",
            "prev_id": "03_1543_12",
            "next_id": "03_1543_14",
            "characters": [
                "C001",
                "C007",
                "C002",
                "C003"
            ],
            "stage": "Ups & Downs",
            "storyline": "C007는 본능적인 적대감을 느낀다.",
            "unit_motif": "계급을 초월한 사랑",
            "causality": "Temptation(유혹)",
            "story_scripts": [
                {
                    "type": "narrative",
                    "location": "집앞",
                    "character": [
                        "C001",
                        "C007"
                    ],
                    "act": "때리다",
                    "emotion": "괘씸하다",
                    "content": "C007가 빨래를 더럽힌다."
                },
                {
                    "type": "narrative",
                    "location": "집앞",
                    "character": [
                        "C001",
                        "C007"
                    ],
                    "act": "때리다",
                    "emotion": "괴롭다",
                    "content": "C001는 C007의 뺨을 때린다."
                },
                {
                    "type": "narrative",
                    "location": "방",
                    "character": [
                        "C001"
                    ],
                    "act": "찾는다",
                    "content": "C001가 방으로 돌아온다."
                },
                {
                    "type": "narrative",
                    "location": "방",
                    "character": [
                        "C001"
                    ],
                    "act": "찾는다",
                    "content": "C001는 C007가 자신의 물건들을 다 망가뜨린 것을 본다."
                },
                {
                    "type": "narrative",
                    "location": "화실",
                    "character": [
                        "C001",
                        "C002"
                    ],
                    "act": "명령하다",
                    "content": "C002가 그림을 그린다."
                },
                {
                    "type": "narrative",
                    "location": "화실",
                    "character": [
                        "C001",
                        "C002"
                    ],
                    "act": "명령하다",
                    "content": "C001는 자리를 피하려고 한다."
                },
                {
                    "type": "narrative",
                    "location": "화실",
                    "character": [
                        "C001",
                        "C002"
                    ],
                    "act": "명령하다",
                    "content": "하지만 C002는 그대로 있으라고 말한다."
                },
                {
                    "type": "narrative",
                    "location": "화실",
                    "character": [
                        "C001",
                        "C002"
                    ],
                    "act": "명령하다",
                    "content": "C002가 물감 심부름을 시킨다."
                },
                {
                    "type": "narrative",
                    "location": "거리",
                    "character": [
                        "C001",
                        "C003"
                    ],
                    "act": "다투다/대립하다",
                    "content": "C001가 C003와 거리를 걷는다."
                },
                {
                    "type": "narrative",
                    "location": "거리",
                    "character": [
                        "C001",
                        "C003"
                    ],
                    "act": "다투다/대립하다",
                    "content": "C003는 C001에게 머리카락을 보여달라고 하지만, C001는 거절한다."
                }
            ]
        },
        {
            "id": "03_1543_14",
            "prev_id": "03_1543_13",
            "next_id": "03_1543_15",
            "characters": [
                "C001",
                "C002",
                "C006"
            ],
            "stage": "Defeat",
            "storyline": "C002는 C001를 계속 그린다.",
            "unit_motif": "고귀한 하녀",
            "causality": "Distortion(뒤틀림/왜곡)",
            "story_scripts": [
                {
                    "type": "narrative",
                    "location": "화실",
                    "character": [
                        "C001",
                        "C002"
                    ],
                    "act": "말하다",
                    "content": "C001가 청소를 한다."
                },
                {
                    "type": "narrative",
                    "location": "화실",
                    "character": [
                        "C001",
                        "C002"
                    ],
                    "act": "말하다",
                    "content": "C002가 C001를 한참 바라본다."
                },
                {
                    "type": "narrative",
                    "location": "화실",
                    "character": [
                        "C001",
                        "C002"
                    ],
                    "act": "말하다",
                    "content": "C002는 C004과 한자리에 있지는 않지만, C001를 그릴 것임을 알린다."
                },
                {
                    "type": "narrative",
                    "location": "집",
                    "character": [
                        "C001",
                        "C006"
                    ],
                    "act": "준다",
                    "emotion": "괘씸하다",
                    "content": "C006가 C001에게 급료를 준다."
                },
                {
                    "type": "narrative",
                    "location": "집",
                    "character": [
                        "C001",
                        "C006"
                    ],
                    "act": "준다",
                    "content": "C006는 이미 그 그림에 대해서 알고 있다."
                },
                {
                    "type": "narrative",
                    "location": "강가",
                    "character": [
                        "C001",
                        "C002"
                    ],
                    "act": "명령하다",
                    "content": "C001가 물을 긷는다."
                },
                {
                    "type": "narrative",
                    "location": "강가",
                    "character": [
                        "C001",
                        "C002"
                    ],
                    "act": "명령하다",
                    "content": "C002가 C001에게 다가온다."
                },
                {
                    "type": "narrative",
                    "location": "강가",
                    "character": [
                        "C001",
                        "C002"
                    ],
                    "act": "명령하다",
                    "emotion": "단호하다",
                    "content": "C002는 그녀에게 내일 오전에 시간을 비우라고 말한다."
                },
                {
                    "type": "narrative",
                    "location": "화실",
                    "character": [
                        "C001",
                        "C002"
                    ],
                    "act": "만들다",
                    "content": "C002가 그림을 그린다."
                },
                {
                    "type": "narrative",
                    "location": "화실",
                    "character": [
                        "C001",
                        "C002"
                    ],
                    "act": "만들다",
                    "content": "그러나 뭔가 뜻대로 되지 않는다."
                }
            ]
        },
        {
            "id": "03_1543_15",
            "prev_id": "03_1543_14",
            "next_id": "03_1543_16",
            "characters": [
                "C001",
                "C002",
                "C004",
                "C008"
            ],
            "stage": "Defeat",
            "storyline": "C008는 C001를 질투를 한다.",
            "unit_motif": "고귀한 하녀",
            "causality": "Distortion(뒤틀림/왜곡)",
            "story_scripts": [
                {
                    "type": "narrative",
                    "location": "화실",
                    "character": [
                        "C001",
                        "C002"
                    ],
                    "act": "만들다",
                    "emotion": "궁금하다",
                    "content": "C001 역시 힘들어한다."
                },
                {
                    "type": "narrative",
                    "location": "화실",
                    "character": [
                        "C001",
                        "C002"
                    ],
                    "act": "만들다",
                    "content": "C002가 C001에게 두건을 벗으라고 한다."
                },
                {
                    "type": "narrative",
                    "location": "화실",
                    "character": [
                        "C001",
                        "C002"
                    ],
                    "act": "만들다",
                    "content": "C001는 거절한다."
                },
                {
                    "type": "narrative",
                    "location": "화실",
                    "character": [
                        "C001",
                        "C002"
                    ],
                    "act": "만들다",
                    "content": "C002가 다시 한번 부탁한다."
                },
                {
                    "type": "narrative",
                    "location": "화실",
                    "character": [
                        "C001",
                        "C002"
                    ],
                    "act": "만들다",
                    "content": "C001가 처음으로 두건을 벗는다."
                },
                {
                    "type": "narrative",
                    "location": "창고",
                    "character": [
                        "C001",
                        "C002"
                    ],
                    "act": "간다/이동한다",
                    "content": "C001가 바로 천으로 머리를 감쌀 준비를 한다."
                },
                {
                    "type": "narrative",
                    "location": "창고",
                    "character": [
                        "C001",
                        "C002"
                    ],
                    "act": "간다/이동한다",
                    "content": "그녀의 머리는 갈색 곱슬이다."
                },
                {
                    "type": "narrative",
                    "location": "창고",
                    "character": [
                        "C001",
                        "C002"
                    ],
                    "act": "간다/이동한다",
                    "emotion": "감탄하다",
                    "content": "C002가 C001의 머리카락을 바라본다."
                },
                {
                    "type": "narrative",
                    "location": "집",
                    "character": [
                        "C004",
                        "C008"
                    ],
                    "act": "간다/이동한다",
                    "content": "C004이 C008를 약 올린다."
                },
                {
                    "type": "narrative",
                    "location": "집",
                    "character": [
                        "C004",
                        "C008"
                    ],
                    "act": "간다/이동한다",
                    "content": "C008는 불안해한다."
                }
            ]
        },
        {
            "id": "03_1543_16",
            "prev_id": "03_1543_15",
            "next_id": "03_1543_17",
            "characters": [
                "C001",
                "C008",
                "C002"
            ],
            "stage": "Innermost Cave",
            "storyline": "C002가 그림을 위해 C001에게 진주 귀걸이를 하라고 한다.",
            "unit_motif": "불우한 천재",
            "causality": "Leads to tragedy(비극의 서막)",
            "story_scripts": [
                {
                    "type": "narrative",
                    "location": "집",
                    "character": [
                        "C001",
                        "C008",
                        "C002"
                    ],
                    "act": "간다/이동한다",
                    "content": "C002가 C001를 응시한다."
                },
                {
                    "type": "narrative",
                    "location": "집",
                    "character": [
                        "C001",
                        "C008",
                        "C002"
                    ],
                    "act": "간다/이동한다",
                    "emotion": "거부감",
                    "content": "C008가 그런 C002와 C001를 불만스럽게 바라본다."
                },
                {
                    "type": "narrative",
                    "location": "화실",
                    "character": [
                        "C001",
                        "C002"
                    ],
                    "act": "명령하다",
                    "content": "C002가 C001에게 입을 벌리라고 한다."
                },
                {
                    "type": "narrative",
                    "location": "화실",
                    "character": [
                        "C001",
                        "C002"
                    ],
                    "act": "명령하다",
                    "content": "C002가 C001가 입술을 핥는 모습을 바라본다."
                },
                {
                    "type": "narrative",
                    "location": "집",
                    "character": [
                        "C001",
                        "C008",
                        "C002"
                    ],
                    "act": "간다/이동한다",
                    "content": "C002가 C008에게 귀걸이를 걸어준다."
                },
                {
                    "type": "narrative",
                    "location": "집",
                    "character": [
                        "C001",
                        "C008",
                        "C002"
                    ],
                    "act": "간다/이동한다",
                    "content": "C008는 신경질을 낸다."
                },
                {
                    "type": "narrative",
                    "location": "화실",
                    "character": [
                        "C001",
                        "C002"
                    ],
                    "act": "다투다/대립하다",
                    "content": "C002가 C001에게 진주 귀걸이를 하라고 말한다."
                },
                {
                    "type": "narrative",
                    "location": "화실",
                    "character": [
                        "C001",
                        "C002"
                    ],
                    "act": "다투다/대립하다",
                    "emotion": "괴롭다",
                    "content": "C001는 부담스러워서 싫다고 한다."
                },
                {
                    "type": "narrative",
                    "location": "화실",
                    "character": [
                        "C001",
                        "C002"
                    ],
                    "act": "다투다/대립하다",
                    "content": "C002가 C001에게 그림을 보여준다."
                },
                {
                    "type": "narrative",
                    "location": "화실",
                    "character": [
                        "C001",
                        "C002"
                    ],
                    "act": "다투다/대립하다",
                    "content": "C001는 그림을 보고 굴복하고 만다."
                }
            ]
        },
        {
            "id": "03_1543_17",
            "prev_id": "03_1543_16",
            "next_id": "03_1543_18",
            "characters": [
                "C001",
                "C002",
                "C004",
                "C006"
            ],
            "stage": "Innermost Cave",
            "storyline": "C004이 C001를 겁탈하려 하고, C006는 C001에게 경고한다.",
            "unit_motif": "불우한 천재",
            "causality": "Leads to tragedy(비극의 서막)",
            "story_scripts": [
                {
                    "type": "narrative",
                    "location": "화실",
                    "character": [
                        "C001",
                        "C002"
                    ],
                    "act": "다투다/대립하다",
                    "emotion": "난감하다",
                    "content": "C001가 진주 귀걸이를 한다."
                },
                {
                    "type": "narrative",
                    "location": "화실",
                    "character": [
                        "C001",
                        "C002"
                    ],
                    "act": "다투다/대립하다",
                    "content": "C002가 그림을 그린다."
                },
                {
                    "type": "narrative",
                    "location": "집앞",
                    "character": [
                        "C001",
                        "C004"
                    ],
                    "act": "위협하다/협박하다",
                    "content": "C001가 빨래를 널고 있다."
                },
                {
                    "type": "narrative",
                    "location": "집앞",
                    "character": [
                        "C001",
                        "C004"
                    ],
                    "act": "위협하다/협박하다",
                    "content": "C004이 그런 C001를 탐욕스럽게 바라본다."
                },
                {
                    "type": "narrative",
                    "location": "집앞",
                    "character": [
                        "C001",
                        "C004"
                    ],
                    "act": "위협하다/협박하다",
                    "content": "C004이 C001를 겁탈하려 한다."
                },
                {
                    "type": "narrative",
                    "location": "화실",
                    "character": [
                        "C001"
                    ],
                    "act": "만들다",
                    "content": "C001가 물감을 만들고 있다."
                },
                {
                    "type": "narrative",
                    "location": "화실",
                    "character": [
                        "C001"
                    ],
                    "act": "만들다",
                    "content": "C001의 목에 상처가 나 있다."
                },
                {
                    "type": "narrative",
                    "location": "화실",
                    "character": [
                        "C001",
                        "C006"
                    ],
                    "act": "말하다",
                    "content": "C006가 물감을 만드는 C001에게 찾아온다."
                },
                {
                    "type": "narrative",
                    "location": "화실",
                    "character": [
                        "C001",
                        "C006"
                    ],
                    "act": "말하다",
                    "emotion": "괘씸하다",
                    "content": "C006는 C004의 심기를 거스르지 말라고 한다."
                },
                {
                    "type": "narrative",
                    "location": "집",
                    "character": [
                        "C001",
                        "C006"
                    ],
                    "act": "간다/이동한다",
                    "content": "C006가 C001에게 귀걸이를 건넨다."
                }
            ]
        },
        {
            "id": "03_1543_18",
            "prev_id": "03_1543_17",
            "next_id": "03_1543_19",
            "characters": [
                "C001",
                "C006",
                "C008",
                "C002"
            ],
            "stage": "Resurrection",
            "storyline": "C008는 자신의 귀걸이를 한 C001를 보고 분노한다.",
            "unit_motif": "대전격투",
            "causality": "Seeker(추적/추구)",
            "story_scripts": [
                {
                    "type": "narrative",
                    "location": "화실",
                    "character": [
                        "C001",
                        "C006",
                        "C008",
                        "C002"
                    ],
                    "act": "모욕하다/욕하다",
                    "emotion": "경멸하다",
                    "content": "C008가 모든 사실을 알고 난리가 난다."
                },
                {
                    "type": "narrative",
                    "location": "화실",
                    "character": [
                        "C001",
                        "C006",
                        "C008",
                        "C002"
                    ],
                    "act": "모욕하다/욕하다",
                    "content": "C008가 울며 소리친다."
                },
                {
                    "type": "narrative",
                    "location": "화실",
                    "character": [
                        "C001",
                        "C006",
                        "C008",
                        "C002"
                    ],
                    "act": "모욕하다/욕하다",
                    "content": "C008가 C002에게 그림을 보여달라고 한다."
                },
                {
                    "type": "narrative",
                    "location": "화실",
                    "character": [
                        "C001",
                        "C006",
                        "C008",
                        "C002"
                    ],
                    "act": "모욕하다/욕하다",
                    "emotion": "괴롭다",
                    "content": "C002가 그런 C008를 차갑게 외면한다."
                },
                {
                    "type": "narrative",
                    "location": "화실",
                    "character": [
                        "C001",
                        "C006",
                        "C008",
                        "C002"
                    ],
                    "act": "모욕하다/욕하다",
                    "content": "C008는 C001가 자신의 진주 귀걸이를 했다는 사실을 알게 된다."
                },
                {
                    "type": "narrative",
                    "location": "화실",
                    "character": [
                        "C001",
                        "C006",
                        "C008",
                        "C002"
                    ],
                    "act": "모욕하다/욕하다",
                    "content": "C008는 C001에게 소리친다."
                },
                {
                    "type": "narrative",
                    "location": "화실",
                    "character": [
                        "C001",
                        "C006",
                        "C008",
                        "C002"
                    ],
                    "act": "모욕하다/욕하다",
                    "content": "C008는 둘에게 매우 분노한다."
                },
                {
                    "type": "narrative",
                    "location": "화실",
                    "character": [
                        "C001",
                        "C006",
                        "C008",
                        "C002"
                    ],
                    "act": "모욕하다/욕하다",
                    "content": "C008가 C002에게 계속 그림을 보여달라고 소리친다."
                },
                {
                    "type": "narrative",
                    "location": "화실",
                    "character": [
                        "C001",
                        "C006",
                        "C008",
                        "C002"
                    ],
                    "act": "모욕하다/욕하다",
                    "content": "C002는 그런 C008에 난감해한다."
                },
                {
                    "type": "narrative",
                    "location": "화실",
                    "character": [
                        "C001",
                        "C006",
                        "C008",
                        "C002"
                    ],
                    "act": "부수다",
                    "content": "C002가 계속되는 C008의 청에 그림을 보여준다."
                }
            ]
        },
        {
            "id": "03_1543_19",
            "prev_id": "03_1543_18",
            "characters": [
                "C001",
                "C006",
                "C008",
                "C002"
            ],
            "stage": "Resurrection",
            "storyline": "C001는 어쩔 줄 몰라 하며 눈치를 본다.",
            "unit_motif": "대전격투",
            "causality": "Seeker(추적/추구)",
            "story_scripts": [
                {
                    "type": "narrative",
                    "location": "화실",
                    "character": [
                        "C001",
                        "C006",
                        "C008",
                        "C002"
                    ],
                    "act": "부수다",
                    "emotion": "참담하다",
                    "content": "C008가 그림을 본다."
                },
                {
                    "type": "narrative",
                    "location": "화실",
                    "character": [
                        "C001",
                        "C006",
                        "C008",
                        "C002"
                    ],
                    "act": "부수다",
                    "content": "C008가 충격을 받는다."
                },
                {
                    "type": "narrative",
                    "location": "화실",
                    "character": [
                        "C001",
                        "C006",
                        "C008",
                        "C002"
                    ],
                    "act": "부수다",
                    "content": "C008가 그림을 칼로 찢으려 한다."
                },
                {
                    "type": "narrative",
                    "location": "화실",
                    "character": [
                        "C001",
                        "C006",
                        "C008",
                        "C002"
                    ],
                    "act": "부수다",
                    "content": "C002가 C008를 말린다."
                },
                {
                    "type": "narrative",
                    "location": "화실",
                    "character": [
                        "C001",
                        "C006",
                        "C008",
                        "C002"
                    ],
                    "act": "부수다",
                    "content": "C002가 C008의 시선을 외면한다."
                },
                {
                    "type": "narrative",
                    "location": "화실",
                    "character": [
                        "C001",
                        "C006",
                        "C008",
                        "C002"
                    ],
                    "act": "부수다",
                    "content": "C008가 오열한다."
                },
                {
                    "type": "narrative",
                    "location": "화실",
                    "character": [
                        "C001",
                        "C006",
                        "C008",
                        "C002"
                    ],
                    "act": "부수다",
                    "content": "C001는 어쩔 줄 몰라 한다."
                },
                {
                    "type": "narrative",
                    "location": "화실",
                    "character": [
                        "C001",
                        "C006",
                        "C008",
                        "C002"
                    ],
                    "act": "위협하다/협박하다",
                    "emotion": "경멸하다",
                    "content": "C008가 C001에게 나가라고 소리친다."
                },
                {
                    "type": "narrative",
                    "location": "화실",
                    "character": [
                        "C001",
                        "C006",
                        "C008",
                        "C002"
                    ],
                    "act": "위협하다/협박하다",
                    "content": "C001는 방을 나온다."
                },
                {
                    "type": "narrative",
                    "location": "화실",
                    "character": [
                        "C001",
                        "C006",
                        "C008",
                        "C002"
                    ],
                    "act": "위협하다/협박하다",
                    "content": "C001는 방을 나와 마주친 C005의 싸늘한 시선을 느낀다."
                }
            ]
        }
    ]
}