{
    "country": "01",
    "class_1": "05",
    "내용분류": {
        "감정": [
            "놀람"
        ],
        "대화형태": [
            "질문",
            "설명",
            "답변"
        ],
        "행동": [
            "반응",
            "갈등",
            "권유"
        ],
        "인물관계": [
            "연인",
            "친구"
        ],
        "캐릭터": [
            "여성",
            "왕족/귀족",
            "서생",
            "승려"
        ],
        "직업/신분": [
            "신하",
            "승려"
        ],
        "장르": [
            "로맨스"
        ],
        "사건/모티프": [
            "사랑",
            "기적"
        ],
        "공간": [
            "절/신당"
        ]
    },
    "주제어": [
        "노승 보항",
        "이생",
        "술안주",
        "재능",
        "보답"
    ],
    "주제문": "이생은 양파의 선물에 대한 보답을 절의 도움을 받아 하는 것에 부담을 느껴 거절하려 했지만, 노승과 동료들의 강력한 주장에 어쩔 수 없이 수락한다. 그러나 속으로는 이 돈을 언제 갚나 하는 생각을 계속 하고 있었다."
}