{
    "id": "04_1159",
    "type": "comics",
    "title": "누가 짐승인가",
    "genre": [
        "판타지"
    ],
    "year": 1954,
    "theme": "추구",
    "concept": "C003과 C006은 착취만 하는 농장주 C011을 몰아내고 정권을 잡는다. C006은 농장을 단합시키고 발전시키지만 C003은 C006을 몰아내고 정권을 잡고 독재를 시작한다. C003의 정권 아래 가축농장의 동물을 들은 인간 C011이 있었을 때보다 더욱더 많은 착취를 당하게 된다.",
    "structure": "스토리헬퍼 15단계",
    "motif": "독재정치",
    "main_character": "독재자",
    "conflict": "C003과 C006은 농장주 C011을 몰아내고 농장의 전권을 잡지만 C003은 농장의 발전과 모두를 위한 화합을 중요하게 여기던 C006을 처단하고 C003의 독재가 시작된다. C003은 인간 C011 보다 더 악랄하게 동물들을 착취하게 된다.",
    "characters": [
        "C001",
        "C002",
        "C003",
        "C004",
        "C005",
        "C006",
        "C007",
        "C008",
        "C009",
        "C010",
        "C011",
        "C012"
    ],
    "units": [
        {
            "id": "04_1159_01",
            "next_id": "04_1159_02",
            "characters": [
                "C011",
                "C006",
                "C005",
                "C004",
                "C009"
            ],
            "stage": "Main Character",
            "storyline": "C009는 폭력만을 휘두르는 C011을 몰아내야 한다고 주장한다. 그러고는 곧 죽음을 맞는다.",
            "unit_motif": "사디즘",
            "causality": "First Action(시작)",
            "story_scripts": [
                {
                    "type": "narrative",
                    "location": "C011의 농장",
                    "act": "공개하다/드러내다",
                    "emotion": "편안하다",
                    "content": "봄이 찾아온 아름다운 동산의 모습과 함께 C011의 농장이 보인다."
                },
                {
                    "type": "narrative",
                    "location": "술집",
                    "character": [
                        "C011"
                    ],
                    "act": "마시다",
                    "emotion": "즐겁다",
                    "content": "C011은 변변찮은 친구들과 함께 술에 빠져 있다."
                },
                {
                    "type": "narrative",
                    "location": "C011의 농장",
                    "character": [
                        "C011"
                    ],
                    "act": "때리다",
                    "emotion": "짜증나다",
                    "content": "술에 취한 C011은 공연히 동물들에게 행패를 부린다."
                },
                {
                    "type": "narrative",
                    "location": "헛간",
                    "character": [
                        "C006",
                        "C005",
                        "C004"
                    ],
                    "act": "간다/이동한다",
                    "emotion": "담담하다",
                    "content": "농장에 사는 모든 동물들이 회의를 하기 위해 C009가 있는 마구간으로 모인다."
                },
                {
                    "type": "narrative",
                    "location": "헛간",
                    "character": [
                        "C009"
                    ],
                    "act": "소리치다",
                    "emotion": "단호하다",
                    "content": "C009는 폭력만을 휘두르는 C011을 몰아내야 한다고 주장한다."
                },
                {
                    "type": "narrative",
                    "location": "헛간",
                    "character": [
                        "C009"
                    ],
                    "act": "소리치다",
                    "emotion": "비장하다",
                    "content": "그러면서 그는 혁명을 선포한다."
                },
                {
                    "type": "narrative",
                    "location": "C011의 집",
                    "character": [
                        "C011"
                    ],
                    "act": "위협하다/협박하다",
                    "emotion": "괘씸하다",
                    "content": "C011이 헛간을 향해 공포탄을 쏘아 댄다."
                },
                {
                    "type": "narrative",
                    "location": "헛간",
                    "character": [
                        "C006",
                        "C005",
                        "C004"
                    ],
                    "act": "도망치다",
                    "emotion": "무섭다",
                    "content": "동물들은 헛간에서 나와 각자 살고 있는 공간으로 흩어진다."
                },
                {
                    "type": "narrative",
                    "location": "C011의 집",
                    "character": [
                        "C011"
                    ],
                    "act": "포박하다/체포하다",
                    "emotion": "통쾌하다",
                    "content": "동물들이 각자 살고 있는 곳으로 돌아가자 C011은 유리창을 닫고 돌아선다."
                },
                {
                    "type": "narrative",
                    "location": "마구간",
                    "character": [
                        "C009"
                    ],
                    "act": "죽이다",
                    "emotion": "안타깝다",
                    "content": "사망한 C009의 모습이 보인다."
                }
            ]
        },
        {
            "id": "04_1159_02",
            "prev_id": "04_1159_01",
            "next_id": "04_1159_03",
            "characters": [
                "C011",
                "C006",
                "C005",
                "C004"
            ],
            "stage": "Setting-up",
            "storyline": "먹을 것이 없어 괴로워하던 동물들은 C011을 농장 밖으로 내쫓아 버린다.",
            "unit_motif": "무장봉기",
            "causality": "New personality(새로운 자아)",
            "story_scripts": [
                {
                    "type": "narrative",
                    "location": "동산",
                    "act": "공개하다/드러내다",
                    "content": "어느새 새벽이 밝아오고 있다."
                },
                {
                    "type": "narrative",
                    "location": "C011의 방",
                    "character": [
                        "C011"
                    ],
                    "act": "자다/잠들다",
                    "emotion": "피곤하다",
                    "content": "깊은 잠에 빠져있는 C011의 모습이 보인다."
                },
                {
                    "type": "narrative",
                    "location": "농장",
                    "act": "다투다/대립하다",
                    "emotion": "괴롭다",
                    "content": "동물들은 먹을 것이 없어 괴로워한다."
                },
                {
                    "type": "narrative",
                    "location": "C011의 방",
                    "character": [
                        "C011"
                    ],
                    "act": "증명하다/입증하다",
                    "emotion": "기대되다",
                    "content": "잠든 C011의 허리춤에 걸린 열쇠 다발이 보인다."
                },
                {
                    "type": "narrative",
                    "location": "창고 앞",
                    "character": [
                        "C006",
                        "C005",
                        "C004"
                    ],
                    "act": "부수다",
                    "emotion": "자신감 있다",
                    "content": "동물들은 힘을 합쳐 창고를 부서뜨린다."
                },
                {
                    "type": "narrative",
                    "location": "C011의 방",
                    "character": [
                        "C011"
                    ],
                    "act": "얻는다/취하다",
                    "emotion": "놀라다",
                    "content": "잠들어 있던 C011이 자리에서 벌떡 일어난다."
                },
                {
                    "type": "narrative",
                    "location": "창고",
                    "character": [
                        "C006",
                        "C005",
                        "C004",
                        "C011"
                    ],
                    "act": "때리다",
                    "emotion": "괘씸하다",
                    "content": "곡식들을 먹어치우는 동물들 앞으로 채찍을 든 C011이 나타난다."
                },
                {
                    "type": "narrative",
                    "location": "창고",
                    "character": [
                        "C006",
                        "C005",
                        "C004",
                        "C011"
                    ],
                    "act": "때리다",
                    "emotion": "단호하다",
                    "content": "하지만 동물들은 C011 앞에서 물러서지 않는다."
                },
                {
                    "type": "narrative",
                    "location": "창고",
                    "character": [
                        "C006",
                        "C005",
                        "C004",
                        "C011"
                    ],
                    "act": "때리다",
                    "emotion": "자신감 있다",
                    "content": "그들은 힘을 합쳐 C011을 창고 밖으로 밀어낸다."
                },
                {
                    "type": "narrative",
                    "location": "농장 입구",
                    "character": [
                        "C006",
                        "C005",
                        "C004",
                        "C011"
                    ],
                    "act": "포박하다/체포하다",
                    "emotion": "황당하다",
                    "content": "동물들은 힘을 합쳐 C011을 농장 밖으로 쫓아낸다."
                },
                {
                    "type": "narrative",
                    "location": "숲길",
                    "character": [
                        "C011"
                    ],
                    "act": "도망치다",
                    "emotion": "무섭다",
                    "content": "C011이 시내로 달아난다."
                },
                {
                    "type": "narrative",
                    "location": "술집 앞",
                    "character": [
                        "C011"
                    ],
                    "act": "간다/이동한다",
                    "emotion": "안심/안도하다",
                    "content": "C011이 술집 안으로 들어간다."
                }
            ]
        },
        {
            "id": "04_1159_03",
            "prev_id": "04_1159_02",
            "next_id": "04_1159_04",
            "characters": [
                "C006",
                "C005",
                "C004",
                "C011"
            ],
            "stage": "1st Accident",
            "storyline": "C006의 주도 아래 동물들은 몰려든 사람들을 물리쳐 낸다.",
            "unit_motif": "대체역사",
            "causality": "Crisis of the heart(지극한 슬픔)",
            "story_scripts": [
                {
                    "type": "narrative",
                    "location": "창고",
                    "character": [
                        "C006",
                        "C005",
                        "C004"
                    ],
                    "act": "먹는다",
                    "emotion": "행복하다",
                    "content": "동물들은 창고 안에 있는 곡식들로 풍족한 식사를 한다."
                },
                {
                    "type": "narrative",
                    "location": "술집 앞",
                    "character": [
                        "C011"
                    ],
                    "act": "위협하다/협박하다",
                    "emotion": "화나다",
                    "content": "C011과 마을 사람들이 연장을 들고 술집을 나선다."
                },
                {
                    "type": "narrative",
                    "location": "술집 앞",
                    "character": [
                        "C011"
                    ],
                    "act": "위협하다/협박하다",
                    "emotion": "괘씸하다",
                    "content": "그들은 곧장 농장으로 향한다."
                },
                {
                    "type": "narrative",
                    "location": "농장",
                    "character": [
                        "C006"
                    ],
                    "act": "만들다",
                    "emotion": "자신감 있다",
                    "content": "C006의 지시에 따라 동물들은 각자의 구역으로 흩어진다."
                },
                {
                    "type": "narrative",
                    "location": "농장 입구",
                    "character": [
                        "C006",
                        "C011"
                    ],
                    "act": "위협하다/협박하다",
                    "emotion": "긴장되다",
                    "content": "가축농장으로 향하는 사람들 모습과 공격 태세를 갖추고 있는 동물들의 모습이 보인다."
                },
                {
                    "type": "narrative",
                    "location": "농장 입구",
                    "character": [
                        "C006",
                        "C011"
                    ],
                    "act": "때리다",
                    "emotion": "단호하다",
                    "content": "거위들이 사람들을 향해 달려든다."
                },
                {
                    "type": "narrative",
                    "location": "농장 입구",
                    "character": [
                        "C006",
                        "C011"
                    ],
                    "act": "때리다",
                    "emotion": "자신감 있다",
                    "content": "하지만 C011을 비롯한 사람들이 아무렇지 않게 이들을 물리친다."
                },
                {
                    "type": "narrative",
                    "location": "농장",
                    "character": [
                        "C006",
                        "C011"
                    ],
                    "act": "도망치다",
                    "emotion": "단호하다",
                    "content": "C006을 비롯한 동물들이 사람들을 물리친다."
                },
                {
                    "type": "narrative",
                    "location": "농장",
                    "character": [
                        "C006",
                        "C011"
                    ],
                    "act": "도망치다",
                    "emotion": "무섭다",
                    "content": "겁에 질린 사람들은 그대로 농장 밖으로 달아난다."
                },
                {
                    "type": "narrative",
                    "location": "농장",
                    "character": [
                        "C006",
                        "C011"
                    ],
                    "act": "도망치다",
                    "emotion": "괴롭다",
                    "content": "이 과정에서 C006은 다리에 총상을 입게 된다."
                }
            ]
        },
        {
            "id": "04_1159_04",
            "prev_id": "04_1159_03",
            "next_id": "04_1159_05",
            "characters": [
                "C001",
                "C006",
                "C005",
                "C004",
                "C003"
            ],
            "stage": "1st Accident",
            "storyline": "자신들을 억압하던 C011의 도구들을 모아 모조리 불태워 버린다.",
            "unit_motif": "대체역사",
            "causality": "Showdown(결전)",
            "story_scripts": [
                {
                    "type": "narrative",
                    "location": "농장",
                    "character": [
                        "C001"
                    ],
                    "act": "증명하다/입증하다",
                    "emotion": "안타깝다",
                    "content": "죽은 C001와 그의 어린 새끼들의 모습이 보인다."
                },
                {
                    "type": "narrative",
                    "location": "농장",
                    "character": [
                        "C006",
                        "C005",
                        "C004"
                    ],
                    "act": "만들다",
                    "emotion": "단호하다",
                    "content": "동물들은 C011이 자신들을 억압하기 위해 사용하던 칼과 족쇄 같은 도구들을 모조리 마당 한쪽에 모아둔다."
                },
                {
                    "type": "narrative",
                    "location": "농장",
                    "character": [
                        "C006",
                        "C005",
                        "C004"
                    ],
                    "act": "부수다",
                    "emotion": "비장하다",
                    "content": "동물들은 C011이 사용하던 물건들을 모조리 불에 태운다."
                },
                {
                    "type": "narrative",
                    "location": "농장",
                    "character": [
                        "C006",
                        "C005",
                        "C004"
                    ],
                    "act": "부수다",
                    "emotion": "기쁘다",
                    "content": "그들은 불가에 둘러서서 기쁨의 노래를 부른다."
                },
                {
                    "type": "narrative",
                    "location": "C011의 집 앞",
                    "character": [
                        "C006",
                        "C003"
                    ],
                    "act": "간다/이동한다",
                    "emotion": "기대되다",
                    "content": "C006과 C003을 위시한 동물들이 C011의 집 안으로 들어간다."
                },
                {
                    "type": "narrative",
                    "location": "C011의 집",
                    "character": [
                        "C006",
                        "C003"
                    ],
                    "act": "다투다/대립하다",
                    "emotion": "당황하다",
                    "content": "동물들은 C011이 사용하던 물건들에 당혹감을 느낀다."
                },
                {
                    "type": "narrative",
                    "location": "C011의 집 앞",
                    "character": [
                        "C006",
                        "C003"
                    ],
                    "act": "만들다",
                    "emotion": "단호하다",
                    "content": "C006을 비롯한 동물들은 C011의 집이 필요 없는 곳이라고 생각한다."
                },
                {
                    "type": "narrative",
                    "location": "C011의 집 앞",
                    "character": [
                        "C006",
                        "C003"
                    ],
                    "act": "만들다",
                    "emotion": "단호하다",
                    "content": "곧 커다란 자물쇠로 C011의 집을 잠가 둔다."
                },
                {
                    "type": "narrative",
                    "location": "C011의 집 앞",
                    "character": [
                        "C006",
                        "C003"
                    ],
                    "act": "만들다",
                    "emotion": "의심스럽다",
                    "content": "그런데 C003은 다른 생각을 하고 있다."
                },
                {
                    "type": "narrative",
                    "location": "C011의 집 앞",
                    "character": [
                        "C003"
                    ],
                    "act": "받는다",
                    "emotion": "애틋하다",
                    "content": "C003은 C011은 집 안에 있던 새끼 C001들을 다락방 안으로 옮겨다 놓는다."
                }
            ]
        },
        {
            "id": "04_1159_05",
            "prev_id": "04_1159_04",
            "next_id": "04_1159_06",
            "characters": [
                "C006",
                "C004",
                "C003",
                "C007",
                "C005"
            ],
            "stage": "Doubts & Debate",
            "storyline": "가축농장은 동물 스스로가 꾸려가는 농장이 된다. 그리고 이는 큰 성공을 거둔다.",
            "unit_motif": "운명에 대한 반역",
            "causality": "Touch of the death(애석한 죽음)",
            "story_scripts": [
                {
                    "type": "narrative",
                    "location": "농장",
                    "character": [
                        "C006"
                    ],
                    "act": "만들다",
                    "emotion": "비장하다",
                    "content": "동물들의 우두머리가 된 C006은 농장의 이름을 동물 농장이라 명명한다."
                },
                {
                    "type": "narrative",
                    "location": "농장",
                    "character": [
                        "C006"
                    ],
                    "act": "만들다",
                    "emotion": "단호하다",
                    "content": "그리고 동물 농장의 법을 모두가 볼 수 있는 자리에 기록해 둔다."
                },
                {
                    "type": "narrative",
                    "location": "동물 농장",
                    "act": "지키다/보호하다",
                    "emotion": "기대되다",
                    "content": "가축농장은 이제 동물 스스로 꾸려가는 농장이 되어있다."
                },
                {
                    "type": "narrative",
                    "location": "동물 농장",
                    "act": "지키다/보호하다",
                    "emotion": "자신감 있다",
                    "content": "동물들에게 문제가 생기면 C003이 나서서 어려움을 해결해 준다."
                },
                {
                    "type": "narrative",
                    "location": "들판",
                    "character": [
                        "C004"
                    ],
                    "act": "만들다",
                    "emotion": "보람차다",
                    "content": "C005를 비롯한 동물들은 힘을 합쳐 농사를 짓는다."
                },
                {
                    "type": "narrative",
                    "location": "들판",
                    "character": [
                        "C004"
                    ],
                    "act": "만들다",
                    "emotion": "만족하다",
                    "content": "그들은 손발이 척척 잘 맞는다."
                },
                {
                    "type": "narrative",
                    "location": "동물 농장",
                    "character": [
                        "C003",
                        "C007"
                    ],
                    "act": "놀다",
                    "emotion": "불안하다",
                    "content": "교활한 C003과 그의 동반자 C007가 소개된다."
                },
                {
                    "type": "narrative",
                    "location": "동물 농장",
                    "character": [
                        "C003",
                        "C007"
                    ],
                    "act": "놀다",
                    "emotion": "편안하다",
                    "content": "다른 동물들이 들에 나가는 동안 그 둘은 물이나 마시며 시간을 보낸다."
                },
                {
                    "type": "narrative",
                    "location": "들판",
                    "character": [
                        "C005",
                        "C004"
                    ],
                    "act": "만들다",
                    "emotion": "보람차다",
                    "content": "동물들은 힘을 합쳐 볏짚을 쌓아 올린다."
                },
                {
                    "type": "narrative",
                    "location": "들판",
                    "character": [
                        "C005",
                        "C004"
                    ],
                    "emotion": "뿌듯하다",
                    "content": "동물들은 자신의 일에 뿌듯함을 느낀다."
                }
            ]
        },
        {
            "id": "04_1159_06",
            "prev_id": "04_1159_05",
            "next_id": "04_1159_07",
            "characters": [
                "C011",
                "C006",
                "C002",
                "C012"
            ],
            "stage": "Doubts & Debate",
            "storyline": "가축농장은 이는 큰 성공을 거둔다. 그것을 본 C011은 동물들의 배신을 이야기하지만 방법을 찾지 못한다.",
            "unit_motif": "운명에 대한 반역",
            "causality": "Catharsis(카타르시스)",
            "story_scripts": [
                {
                    "type": "narrative",
                    "location": "언덕",
                    "character": [
                        "C011"
                    ],
                    "act": "찾는다",
                    "emotion": "부럽다",
                    "content": "C011은 동물들이 일궈놓은 들판을 바라본다."
                },
                {
                    "type": "narrative",
                    "location": "술집",
                    "character": [
                        "C011"
                    ],
                    "act": "간다/이동한다",
                    "emotion": "참담하다",
                    "content": "C011이 술집 안으로 들어간다."
                },
                {
                    "type": "narrative",
                    "location": "언덕",
                    "character": [
                        "C011"
                    ],
                    "act": "포박하다/체포하다",
                    "emotion": "편안하다",
                    "content": "풍요로운 들판과 곡식들이 가득 들어찬 창고의 모습이 보인다."
                },
                {
                    "type": "narrative",
                    "location": "헛간",
                    "character": [
                        "C006"
                    ],
                    "act": "말하다",
                    "emotion": "뿌듯하다",
                    "content": "C006은 지난 5달 동안 자신들이 이룬 성과를 공표한다."
                },
                {
                    "type": "narrative",
                    "location": "헛간",
                    "character": [
                        "C006"
                    ],
                    "act": "말하다",
                    "emotion": "담담하다",
                    "content": "그는 새들을 시켜 자신들의 성공을 다른 농장에 전파하도록 한다."
                },
                {
                    "type": "narrative",
                    "location": "다른 헛간",
                    "character": [
                        "C002",
                        "C012"
                    ],
                    "act": "말하다",
                    "emotion": "기대되다",
                    "content": "새들이 가축농장의 소식을 다른 동물들에게 전한다."
                },
                {
                    "type": "narrative",
                    "location": "다른 헛간",
                    "character": [
                        "C002",
                        "C012"
                    ],
                    "act": "말하다",
                    "emotion": "놀라다",
                    "content": "C002는 가축농장의 이야기를 믿지 못해 하고 양은 변화의 이야기를 듣고 겁에 질린다."
                },
                {
                    "type": "narrative",
                    "location": "다른 헛간",
                    "character": [
                        "C002",
                        "C012"
                    ],
                    "act": "말하다",
                    "emotion": "기대되다",
                    "content": "한편 힘든 노동에 시달리던 C012는 솔깃한 반응을 보인다."
                },
                {
                    "type": "narrative",
                    "location": "술집",
                    "character": [
                        "C011"
                    ],
                    "act": "말하다",
                    "emotion": "걱정",
                    "content": "사람들은 동물들의 배신에 대해 많은 이야기를 나눈다."
                },
                {
                    "type": "narrative",
                    "location": "술집",
                    "character": [
                        "C011"
                    ],
                    "act": "말하다",
                    "emotion": "안타깝다",
                    "content": "하지만 그들은 뚜렷한 해결 방법을 찾지 못한다."
                }
            ]
        },
        {
            "id": "04_1159_07",
            "prev_id": "04_1159_06",
            "next_id": "04_1159_08",
            "characters": [
                "C006",
                "C008",
                "C003",
                "C001",
                "C007"
            ],
            "stage": "Making a Choice",
            "storyline": "C003이 이상주의자인 C006을 제거하고 가축농장의 우두머리가 된다.",
            "unit_motif": "모반",
            "causality": "Threshold guardian(마지막 수호자)",
            "story_scripts": [
                {
                    "type": "narrative",
                    "location": "헛간",
                    "character": [
                        "C006"
                    ],
                    "act": "준다",
                    "emotion": "안타깝다",
                    "content": "C006은 동물들에게 언어와 수학을 가르쳐준다. 하지만 동물들은 이를 잘 따라오지 못한다."
                },
                {
                    "type": "narrative",
                    "location": "헛간 외부",
                    "character": [
                        "C008"
                    ],
                    "act": "받아들이다/수락하다",
                    "emotion": "단호하다",
                    "content": "C008이 네 발 동물은 착하고 두 발 동물은 나쁘다고 쓴 가축농장의 법령을 읽는다."
                },
                {
                    "type": "narrative",
                    "location": "헛간",
                    "character": [
                        "C006"
                    ],
                    "act": "만들다",
                    "emotion": "기대되다",
                    "content": "C006은 농장의 동력 문제를 해결하기 위해 풍차를 연구한다."
                },
                {
                    "type": "narrative",
                    "location": "다락방",
                    "character": [
                        "C003"
                    ],
                    "act": "만들다",
                    "emotion": "불안하다",
                    "content": "C003은 어린 C001들을 자신의 친위대로 조직하고 있다."
                },
                {
                    "type": "narrative",
                    "location": "가축농장",
                    "character": [
                        "C006"
                    ],
                    "act": "만들다",
                    "emotion": "혼란스럽다",
                    "content": "1월의 매섭고도 혹독한 날씨가 찾아오자 농장에 기근이 찾아온다."
                },
                {
                    "type": "narrative",
                    "location": "헛간",
                    "character": [
                        "C006"
                    ],
                    "act": "만들다",
                    "emotion": "기대되다",
                    "content": "C006은 풍차에 대한 계획을 완성해 간다."
                },
                {
                    "type": "narrative",
                    "location": "헛간",
                    "character": [
                        "C006",
                        "C003"
                    ],
                    "act": "소리치다",
                    "emotion": "비장하다",
                    "content": "C006은 동물들이 조금 더 일하고 적게 먹는다면 전기를 사용할 수 있게 된다는 자신의 계획을 설파한다."
                },
                {
                    "type": "narrative",
                    "location": "헛간",
                    "character": [
                        "C006",
                        "C003"
                    ],
                    "act": "소리치다",
                    "emotion": "불만족스럽다",
                    "content": "그런데 C003이 이런 C006의 계획을 정면으로 반대하고 나선다."
                },
                {
                    "type": "narrative",
                    "location": "다락방 외부",
                    "character": [
                        "C001"
                    ],
                    "act": "위협하다/협박하다",
                    "emotion": "자신감 있다",
                    "content": "다락방 밖으로 뛰쳐나온 C001들이 헛간으로 달려간다."
                },
                {
                    "type": "narrative",
                    "location": "헛간",
                    "character": [
                        "C006",
                        "C001"
                    ],
                    "act": "도망치다",
                    "emotion": "혼란스럽다",
                    "content": "C001들이 C006을 헛간 밖으로 쫓아낸다."
                },
                {
                    "type": "narrative",
                    "location": "들판",
                    "character": [
                        "C006"
                    ],
                    "act": "죽이다",
                    "emotion": "단호하다",
                    "content": "C001들이 C006을 해치워 버린다."
                },
                {
                    "type": "narrative",
                    "location": "가축농장 입구",
                    "character": [
                        "C003"
                    ],
                    "act": "보고하다",
                    "emotion": "즐겁다",
                    "content": "C003은 C006이 제거됐다는 소식을 보고받는다."
                },
                {
                    "type": "narrative",
                    "location": "헛간",
                    "character": [
                        "C003",
                        "C007"
                    ],
                    "act": "말하다",
                    "emotion": "뻔뻔하다",
                    "content": "C003과 C007가 단상에 오른다."
                },
                {
                    "type": "narrative",
                    "location": "헛간",
                    "character": [
                        "C003",
                        "C007"
                    ],
                    "act": "말하다",
                    "emotion": "뻔뻔하다",
                    "content": "C003은 C006의 진짜 계획은 C011을 다시 불러오는 것이었다고 거짓말을 한다."
                },
                {
                    "type": "narrative",
                    "location": "헛간",
                    "character": [
                        "C003",
                        "C007"
                    ],
                    "act": "말하다",
                    "emotion": "뻔뻔하다",
                    "content": "그러면서 자신이 이제부터 동물들을 보호하겠다고 나선다."
                }
            ]
        },
        {
            "id": "04_1159_08",
            "prev_id": "04_1159_07",
            "next_id": "04_1159_09",
            "characters": [
                "C003",
                "C005",
                "C004"
            ],
            "stage": "2nd Accident",
            "storyline": "동물들은 C003의 지도 아래 풍차 건설에 나선다. 특히나 C005와 C004은 자신들이 할 수 있는 최선의 노력을 다한다.",
            "unit_motif": "강제된 과업",
            "causality": "Crossing(교차)",
            "story_scripts": [
                {
                    "type": "narrative",
                    "location": "언덕",
                    "character": [
                        "C003"
                    ],
                    "act": "만들다",
                    "emotion": "보람차다",
                    "content": "동물들은 C003의 지도 아래 풍차 건설에 나선다."
                },
                {
                    "type": "narrative",
                    "location": "가축농장 입구",
                    "character": [
                        "C005",
                        "C004"
                    ],
                    "act": "얻는다/취하다",
                    "emotion": "피곤하다",
                    "content": "일을 마친 동물들이 농장으로 돌아온다."
                },
                {
                    "type": "narrative",
                    "location": "언덕",
                    "act": "다투다/대립하다",
                    "emotion": "뻔뻔하다",
                    "content": "동물들에게는 최소한의 식량만이 제공되는 반면 C003은 풍족한 식사를 한다."
                },
                {
                    "type": "narrative",
                    "location": "언덕",
                    "character": [
                        "C005",
                        "C004"
                    ],
                    "act": "만들다",
                    "emotion": "보람차다",
                    "content": "C005와 C004은 풍차 건설에 최선에 다한다."
                },
                {
                    "type": "narrative",
                    "location": "언덕",
                    "character": [
                        "C005",
                        "C004"
                    ],
                    "act": "만들다",
                    "content": "어느덧 겨울이 지나고 봄이 온다."
                },
                {
                    "type": "narrative",
                    "location": "언덕",
                    "character": [
                        "C005",
                        "C004"
                    ],
                    "act": "만들다",
                    "emotion": "뿌듯하다",
                    "content": "C005와 C004의 헌신으로 풍차는 많은 부분이 완성되어 있다."
                },
                {
                    "type": "narrative",
                    "location": "가축농장 입구",
                    "act": "얻는다/취하다",
                    "emotion": "피곤하다",
                    "content": "일을 마친 동물들이 농장으로 돌아온다."
                },
                {
                    "type": "narrative",
                    "location": "언덕",
                    "character": [
                        "C005",
                        "C004"
                    ],
                    "act": "만들다",
                    "emotion": "보람차다",
                    "content": "다른 동물들이 농장으로 돌아간 뒤에도 C005와 C004은 풍차 만들기를 계속한다."
                },
                {
                    "type": "narrative",
                    "location": "동물 농장",
                    "character": [
                        "C005",
                        "C004"
                    ],
                    "act": "찾는다",
                    "emotion": "피곤하다",
                    "content": "C005와 C004은 저녁이 되어서야 마구간으로 돌아간다."
                },
                {
                    "type": "narrative",
                    "location": "동물 농장",
                    "character": [
                        "C005",
                        "C004"
                    ],
                    "act": "찾는다",
                    "emotion": "놀라다",
                    "content": "그런데 잠시 뒤 그들은 C003이 그들의 무리와 떼를 지어 C011의 집 안으로 들어가는 놀라운 광경을 목격하게 된다."
                },
                {
                    "type": "narrative",
                    "location": "C011의 집",
                    "character": [
                        "C003"
                    ],
                    "act": "자다/잠들다",
                    "emotion": "뻔뻔하다",
                    "content": "C003은 존박의 침대에서 잠을 잔다."
                },
                {
                    "type": "narrative",
                    "location": "C011의 방",
                    "character": [
                        "C003"
                    ],
                    "act": "말하다",
                    "emotion": "담담하다",
                    "content": "새들이 C003에게 C011의 이야기를 들려준다."
                },
                {
                    "type": "narrative",
                    "location": "헛간 외부",
                    "act": "다투다/대립하다",
                    "emotion": "뻔뻔하다",
                    "content": "침대를 쓰면 안 된다는 가축농장의 법령이 침대에서 이불을 덮고 잘 수 없다로 어느새 바뀌어 있다."
                },
                {
                    "type": "narrative",
                    "location": "헛간 외부",
                    "act": "다투다/대립하다",
                    "emotion": "놀라다",
                    "content": "동물들은 이를 의아한 얼굴로 쳐다본다."
                },
                {
                    "type": "narrative",
                    "location": "C011의 집",
                    "character": [
                        "C003"
                    ],
                    "act": "받아들이다/수락하다",
                    "emotion": "의심스럽다",
                    "content": "C003은 집 안에 있는 컵들의 냄새를 맡아본다."
                }
            ]
        },
        {
            "id": "04_1159_09",
            "prev_id": "04_1159_08",
            "next_id": "04_1159_10",
            "characters": [
                "C011",
                "C010",
                "C003",
                "C005",
                "C004",
                "C001"
            ],
            "stage": "Villains Move",
            "storyline": "C003은 상인 C010와 거래하며 폭정을 시작한다.",
            "unit_motif": "독재정치",
            "causality": "Last test(마지막 시험/시련)",
            "story_scripts": [
                {
                    "type": "narrative",
                    "location": "술집",
                    "character": [
                        "C011",
                        "C010"
                    ],
                    "act": "말하다",
                    "emotion": "불안하다",
                    "content": "C011의 이야기를 엿들은 상인 C010가 일을 꾸미려 든다."
                },
                {
                    "type": "narrative",
                    "location": "들판",
                    "character": [
                        "C010"
                    ],
                    "act": "간다/이동한다",
                    "emotion": "기대되다",
                    "content": "C010는 차를 타고 가축농장으로 향한다."
                },
                {
                    "type": "narrative",
                    "location": "들판",
                    "character": [
                        "C010"
                    ],
                    "act": "간다/이동한다",
                    "emotion": "기대되다",
                    "content": "그의 자동차 뒤에는 먹을거리가 잔뜩 실려있다."
                },
                {
                    "type": "narrative",
                    "location": "가축농장",
                    "character": [
                        "C003",
                        "C010"
                    ],
                    "act": "흥정하다/협상하다",
                    "emotion": "기대되다",
                    "content": "C003은 C010가 싣고 온 음식들을 보고 입맛을 다신다."
                },
                {
                    "type": "narrative",
                    "location": "가축농장",
                    "character": [
                        "C003",
                        "C010"
                    ],
                    "act": "간다/이동한다",
                    "emotion": "만족하다",
                    "content": "C010는 저녁이 되어서야 C003 곁을 떠난다."
                },
                {
                    "type": "narrative",
                    "location": "마구간",
                    "character": [
                        "C005",
                        "C004"
                    ],
                    "act": "말하다",
                    "emotion": "비장하다",
                    "content": "C003은 동물들에게 바깥세상과의 거래를 결심했다는 소식을 알린다."
                },
                {
                    "type": "narrative",
                    "location": "헛간 외부",
                    "act": "다투다/대립하다",
                    "emotion": "그립다",
                    "content": "닭들은 그들의 알을 빼앗겨서는 안 된다는 C009의 말을 기억하고 있다."
                },
                {
                    "type": "narrative",
                    "location": "가축농장",
                    "act": "때리다",
                    "emotion": "단호하다",
                    "content": "닭들이 반란을 일으킨다."
                },
                {
                    "type": "narrative",
                    "location": "C011의 집",
                    "character": [
                        "C003"
                    ],
                    "act": "자다/잠들다",
                    "emotion": "놀라다",
                    "content": "C003이 잠에서 깨어난다."
                },
                {
                    "type": "narrative",
                    "location": "가축농장",
                    "character": [
                        "C001"
                    ],
                    "act": "위협하다/협박하다",
                    "emotion": "단호하다",
                    "content": "C003은 친위대인 C001들을 이용해 닭들의 반란을 잠재운다."
                },
                {
                    "type": "narrative",
                    "location": "헛간",
                    "character": [
                        "C003"
                    ],
                    "act": "찾는다",
                    "emotion": "참담하다",
                    "content": "C003은 반란에 가담한 동물들을 색출해낸다."
                },
                {
                    "type": "narrative",
                    "location": "가축농장",
                    "character": [
                        "C001"
                    ],
                    "act": "죽이다",
                    "emotion": "참담하다",
                    "content": "C001들이 반란에 가담한 동물들을 해치운다."
                },
                {
                    "type": "narrative",
                    "location": "가축농장",
                    "character": [
                        "C001"
                    ],
                    "act": "죽이다",
                    "emotion": "뻔뻔하다",
                    "content": "동물은 이유 없이 다른 동물을 죽이지 않는다는 법령 아래 이유 없이라는 새로운 단서가 붙어 있다."
                },
                {
                    "type": "narrative",
                    "location": "가축농장",
                    "character": [
                        "C003"
                    ],
                    "act": "위협하다/협박하다",
                    "emotion": "단호하다",
                    "content": "C003은 혁명 완수를 천명하며 동물들이 부르는 노래를 금지시킨다."
                },
                {
                    "type": "narrative",
                    "location": "가축농장",
                    "character": [
                        "C003"
                    ],
                    "act": "위협하다/협박하다",
                    "emotion": "단호하다",
                    "content": "그러면서 그는 노래를 부르는 자에게는 죽음의 형벌이 있을 거라고 으름장을 놓는다."
                }
            ]
        },
        {
            "id": "04_1159_10",
            "prev_id": "04_1159_09",
            "next_id": "04_1159_11",
            "characters": [
                "C003",
                "C010",
                "C011",
                "C005",
                "C004"
            ],
            "stage": "Defeat",
            "storyline": "동물들은 침입한 인간들을 농장 밖으로 다시 쫓아내지만 이 과정에서 풍차가 부셔 저 버린다.",
            "unit_motif": "대전격투",
            "causality": "Ally(동맹/협력)",
            "story_scripts": [
                {
                    "type": "narrative",
                    "location": "가축농장",
                    "character": [
                        "C003",
                        "C010"
                    ],
                    "act": "흥정하다/협상하다",
                    "emotion": "자신감 있다",
                    "content": "C003과 C010의 거래가 활발하게 이루어진다."
                },
                {
                    "type": "narrative",
                    "location": "가축농장",
                    "character": [
                        "C003",
                        "C010"
                    ],
                    "act": "흥정하다/협상하다",
                    "emotion": "기대되다",
                    "content": "그는 계란과 C010의 물건을 교환한다."
                },
                {
                    "type": "narrative",
                    "location": "술집 앞",
                    "character": [
                        "C010"
                    ],
                    "act": "간다/이동한다",
                    "emotion": "자신감 있다",
                    "content": "C010가 술집 안으로 들어간다."
                },
                {
                    "type": "narrative",
                    "location": "술집",
                    "character": [
                        "C010"
                    ],
                    "act": "얻는다/취하다",
                    "emotion": "즐겁다",
                    "content": "C010는 가축농장과의 거래로 엄청난 이익을 얻었다."
                },
                {
                    "type": "narrative",
                    "location": "술집",
                    "character": [
                        "C010"
                    ],
                    "act": "얻는다/취하다",
                    "emotion": "질투하다",
                    "content": "이에 질투심을 느낀 마을 사람들은 가축농장의 풍차를 없애버리겠다고 나선다."
                },
                {
                    "type": "narrative",
                    "location": "술집",
                    "act": "위협하다/협박하다",
                    "emotion": "화나다",
                    "content": "마을 사람들은 각자 연장을 챙겨 가축농장으로 향한다."
                },
                {
                    "type": "narrative",
                    "location": "C011의 집",
                    "character": [
                        "C003"
                    ],
                    "act": "말하다",
                    "emotion": "놀라다",
                    "content": "새들이 C003에게 마을 사람들의 침입 소식을 전한다."
                },
                {
                    "type": "narrative",
                    "location": "가축농장",
                    "character": [
                        "C003",
                        "C011"
                    ],
                    "act": "말하다",
                    "emotion": "비장하다",
                    "content": "C003은 동물들을 모아놓고 농장을 지켜야 한다고 역설한다."
                },
                {
                    "type": "narrative",
                    "location": "C011의 집",
                    "character": [
                        "C003",
                        "C011"
                    ],
                    "act": "말하다",
                    "emotion": "비장하다",
                    "content": "같은 시간 C011은 다이너마이트를 창고에서 챙겨 나온다."
                },
                {
                    "type": "narrative",
                    "location": "언덕",
                    "character": [
                        "C011"
                    ],
                    "act": "위협하다/협박하다",
                    "emotion": "단호하다",
                    "content": "C011은 다이너마이트를 들고 풍차로 향한다."
                },
                {
                    "type": "narrative",
                    "location": "가축농장",
                    "character": [
                        "C003",
                        "C005",
                        "C004"
                    ],
                    "act": "때리다",
                    "emotion": "자신감 있다",
                    "content": "동물들은 힘을 합쳐 인간들을 농장 밖으로 쫓아낸다."
                },
                {
                    "type": "narrative",
                    "location": "가축농장",
                    "character": [
                        "C003",
                        "C005",
                        "C004"
                    ],
                    "act": "때리다",
                    "emotion": "뻔뻔하다",
                    "content": "C003은 이 과정에서 한쪽으로 몸을 피하는 비겁함을 보여준다."
                },
                {
                    "type": "narrative",
                    "location": "가축농장",
                    "character": [
                        "C003"
                    ],
                    "act": "부수다",
                    "emotion": "뻔뻔하다",
                    "content": "C003은 승리를 자죽 하며 자신의 가슴에 커다란 훈장을 단다."
                },
                {
                    "type": "narrative",
                    "location": "가축농장",
                    "character": [
                        "C003"
                    ],
                    "act": "부수다",
                    "emotion": "놀라다",
                    "content": "그런데 이때 풍차가 폭발을 일으킨다."
                },
                {
                    "type": "narrative",
                    "location": "가축농장",
                    "character": [
                        "C003"
                    ],
                    "act": "부수다",
                    "emotion": "서럽다",
                    "content": "이를 본 C005는 눈물을 흘린다."
                }
            ]
        },
        {
            "id": "04_1159_11",
            "prev_id": "04_1159_10",
            "next_id": "04_1159_12",
            "characters": [
                "C003",
                "C005",
                "C004",
                "C007"
            ],
            "stage": "Innermost Cave",
            "storyline": "풍차 재건 사업을 하던 C005가 큰 부상을 입게 된다. 그런데 C003은 이런 C005를 C010의 아교 공장에 팔아넘겨 버린다.",
            "unit_motif": "배반자",
            "causality": "Enemy(적/적대자)",
            "story_scripts": [
                {
                    "type": "narrative",
                    "location": "언덕",
                    "character": [
                        "C003"
                    ],
                    "act": "만들다",
                    "emotion": "보람차다",
                    "content": "눈이 내리는 겨울, C005와 C004을 주축으로 풍차 재건에 나선다."
                },
                {
                    "type": "narrative",
                    "location": "C011의 집",
                    "character": [
                        "C003"
                    ],
                    "act": "놀다",
                    "emotion": "행복하다",
                    "content": "C003은 게임을 하며 한가한 시간을 보내고 풍부한 음식에 둘러싸여 지낸다."
                },
                {
                    "type": "narrative",
                    "location": "가축농장",
                    "character": [
                        "C005",
                        "C004"
                    ],
                    "act": "얻는다/취하다",
                    "emotion": "피곤하다",
                    "content": "C005와 C004 그리고 나머지 동물들은 늦은 저녁이 되어서야 농장으로 돌아온다."
                },
                {
                    "type": "narrative",
                    "location": "언덕",
                    "character": [
                        "C005",
                        "C004"
                    ],
                    "act": "만들다",
                    "emotion": "애틋하다",
                    "content": "C005와 C004은 풍차 재건에 자신들의 모든 것을 쏟아붓는다."
                },
                {
                    "type": "narrative",
                    "location": "C011의 집 앞",
                    "character": [
                        "C003"
                    ],
                    "act": "놀다",
                    "emotion": "편안하다",
                    "content": "C003이 새끼들을 데리고 밖으로 나온다."
                },
                {
                    "type": "narrative",
                    "location": "C011의 집 앞",
                    "character": [
                        "C003"
                    ],
                    "act": "놀다",
                    "emotion": "뻔뻔하다",
                    "content": "그는 아이들이 노는 모습을 보고 흐뭇한 미소를 짓는다."
                },
                {
                    "type": "narrative",
                    "location": "언덕",
                    "character": [
                        "C005",
                        "C004"
                    ],
                    "act": "만들다",
                    "emotion": "피곤하다",
                    "content": "C005와 C004은 쉴 새 없이 일한다."
                },
                {
                    "type": "narrative",
                    "location": "언덕",
                    "character": [
                        "C005",
                        "C004"
                    ],
                    "act": "만들다",
                    "emotion": "안타깝다",
                    "content": "그런데 C005의 다친 발이 자꾸만 나빠져 간다."
                },
                {
                    "type": "narrative",
                    "location": "언덕",
                    "character": [
                        "C005",
                        "C004"
                    ],
                    "act": "해치다",
                    "emotion": "안타깝다",
                    "content": "C005는 풍차 외벽을 쌓는 도중 큰 부상을 입게 된다."
                },
                {
                    "type": "narrative",
                    "location": "C011의 집",
                    "character": [
                        "C003",
                        "C007"
                    ],
                    "act": "말하다",
                    "emotion": "담담하다",
                    "content": "C007가 C003에게 C005의 부상 소식을 전한다."
                },
                {
                    "type": "narrative",
                    "location": "마구간",
                    "character": [
                        "C005",
                        "C004"
                    ],
                    "act": "지키다/보호하다",
                    "emotion": "안타깝다",
                    "content": "C004이 다친 C005를 돌봐준다."
                },
                {
                    "type": "narrative",
                    "location": "마구간",
                    "character": [
                        "C005",
                        "C004"
                    ],
                    "act": "지키다/보호하다",
                    "emotion": "기대되다",
                    "content": "C004은 복사가 충분한 휴식과 퇴직을 제공받을 거라 기대하고 있다."
                },
                {
                    "type": "narrative",
                    "location": "마구간",
                    "character": [
                        "C005",
                        "C004"
                    ],
                    "act": "위협하다/협박하다",
                    "emotion": "불안하다",
                    "content": "가축농장 안으로 트럭 한 대가 나타난다."
                },
                {
                    "type": "narrative",
                    "location": "마구간",
                    "character": [
                        "C005",
                        "C004"
                    ],
                    "act": "위협하다/협박하다",
                    "emotion": "놀라다",
                    "content": "C004은 곧 동료들이 일하고 있는 언덕으로 달려간다."
                },
                {
                    "type": "narrative",
                    "location": "언덕",
                    "character": [
                        "C004"
                    ],
                    "act": "간다/이동한다",
                    "emotion": "의심스럽다",
                    "content": "C004이 동료들을 가축농장으로 데리고 간다."
                },
                {
                    "type": "narrative",
                    "location": "마구간",
                    "character": [
                        "C004"
                    ],
                    "act": "증명하다/입증하다",
                    "emotion": "의심스럽다",
                    "content": "가축농장에 나타난 트럭은 C010가 운영하는 아교 공장에서 온 장의차로 밝혀진다."
                },
                {
                    "type": "narrative",
                    "location": "거리",
                    "character": [
                        "C005",
                        "C004"
                    ],
                    "act": "도망치다",
                    "emotion": "안타깝다",
                    "content": "C004이 트럭 뒤를 쫓아가 보지만 트럭은 저 멀리 달아나 버린다."
                }
            ]
        },
        {
            "id": "04_1159_12",
            "prev_id": "04_1159_11",
            "next_id": "04_1159_13",
            "characters": [
                "C003",
                "C004",
                "C007"
            ],
            "stage": "Choice to Fight",
            "storyline": "C004은 C003 일당에게 큰 분노를 느끼지만 C003을 지키는 C001들 때문에 별다른 저항을 하지 못한다. 한편 C003은 C005의 생명을 팔아 얻은 위스키로 파티를 벌이고 사업을 점차 확장해 간다.",
            "unit_motif": "배반자",
            "causality": "Retaliation(보복/복수)",
            "story_scripts": [
                {
                    "type": "narrative",
                    "location": "C011의 집",
                    "character": [
                        "C003",
                        "C004"
                    ],
                    "act": "얻는다/취하다",
                    "emotion": "의심스럽다",
                    "content": "C003 앞으로 위스키 한 박스가 배달된다."
                },
                {
                    "type": "narrative",
                    "location": "C011의 집",
                    "character": [
                        "C003",
                        "C004"
                    ],
                    "act": "얻는다/취하다",
                    "emotion": "귀찮다",
                    "content": "한편 C003은 슬픔에 빠진 C004 일행의 모습을 발견한다."
                },
                {
                    "type": "narrative",
                    "location": "C011의 집 앞",
                    "character": [
                        "C004",
                        "C007"
                    ],
                    "act": "말하다",
                    "emotion": "뻔뻔하다",
                    "content": "C007는 복사가 아교 공장에 팔리지 않았다는 거짓말을 늘어놓는다."
                },
                {
                    "type": "narrative",
                    "location": "C011의 집 앞",
                    "character": [
                        "C004",
                        "C007"
                    ],
                    "act": "말하다",
                    "emotion": "괘씸하다",
                    "content": "C004은 이에 분노를 느끼지만 C003을 지키는 C001들 때문에 할 수 없이 발길을 돌린다."
                },
                {
                    "type": "narrative",
                    "location": "C011의 집",
                    "act": "놀다",
                    "emotion": "뻔뻔하다",
                    "content": "C003은 C005의 생명을 팔아 얻은 위스키로 파티를 벌인다."
                },
                {
                    "type": "narrative",
                    "location": "가축농장",
                    "act": "포박하다/체포하다",
                    "content": "수년이 지난 뒤의 농장 모습이 하나도 변하지 않았다."
                },
                {
                    "type": "narrative",
                    "location": "가축농장",
                    "act": "포박하다/체포하다",
                    "emotion": "심란하다",
                    "content": "혁명은 아스라한 기억으로만 남아있고 C003을 제외한 동물들의 처지는 하나도 낳아지지 않았다."
                },
                {
                    "type": "narrative",
                    "location": "C011의 집",
                    "act": "증명하다/입증하다",
                    "emotion": "뻔뻔하다",
                    "content": "C003은 기업의 경영자들이 되어 있다."
                },
                {
                    "type": "narrative",
                    "location": "거리",
                    "character": [
                        "C004"
                    ],
                    "act": "수색하다",
                    "emotion": "뻔뻔하다",
                    "content": "C003은 차를 타고 가축농장에 새 시대가 왔음을 알리는 환영식을 하러 간다."
                },
                {
                    "type": "narrative",
                    "location": "거리",
                    "character": [
                        "C004"
                    ],
                    "act": "수색하다",
                    "emotion": "괘씸하다",
                    "content": "C004이 이런 C003의 뒤를 쫓아간다."
                },
                {
                    "type": "narrative",
                    "location": "환영식장",
                    "character": [
                        "C004"
                    ],
                    "act": "간다/이동한다",
                    "emotion": "뻔뻔하다",
                    "content": "환영식을 마친 C003이 C011의 집 안으로 들어간다."
                }
            ]
        },
        {
            "id": "04_1159_13",
            "prev_id": "04_1159_12",
            "characters": [
                "C004",
                "C003"
            ],
            "stage": "Resurrection",
            "storyline": "C004은 동물들을 규합해 C003 일당을 쓰러뜨린다. C003 일당을 쓰러뜨린 C004과 나머지 동물들의 모습이 한동안 보인다.",
            "unit_motif": "무장봉기",
            "causality": "Bold approach(과감한 결정)",
            "story_scripts": [
                {
                    "type": "narrative",
                    "location": "헛간 외부",
                    "character": [
                        "C004"
                    ],
                    "act": "다투다/대립하다",
                    "emotion": "뻔뻔하다",
                    "content": "모든 동물은 동등하다는 법령 아래 하지만 몇몇 동물들은 다른 동물보다 비교 우위라는 새로운 법령이 만들어져 있다."
                },
                {
                    "type": "narrative",
                    "location": "헛간 외부",
                    "character": [
                        "C004"
                    ],
                    "act": "다투다/대립하다",
                    "emotion": "억울하다",
                    "content": "C004은 새들로 하여금 가축농장에서 벌어지고 있는 일들을 널리 알리도록 한다."
                },
                {
                    "type": "narrative",
                    "location": "가축농장",
                    "act": "간다/이동한다",
                    "emotion": "비장하다",
                    "content": "농장 밖 수많은 동물들이 가축농장으로 모여든다."
                },
                {
                    "type": "narrative",
                    "location": "C011의 집",
                    "character": [
                        "C003",
                        "C004"
                    ],
                    "act": "증명하다/입증하다",
                    "emotion": "뻔뻔하다",
                    "content": "C003은 동물들에게 더 많은 일을 시키면서도 더 적은 양의 식사를 하게 만든 동물들에게 표창을 수여한다."
                },
                {
                    "type": "narrative",
                    "location": "C011의 집",
                    "character": [
                        "C003",
                        "C004"
                    ],
                    "act": "증명하다/입증하다",
                    "emotion": "화나다",
                    "content": "C004은 이런 C003의 모습에서 C011의 모습을 발견한다."
                },
                {
                    "type": "narrative",
                    "location": "C011의 집",
                    "character": [
                        "C003",
                        "C004"
                    ],
                    "emotion": "배신감",
                    "content": "C004은 인간의 C011 아래 있을 때보다 C003 아래 있을 때 더 처절한 착취를 당한 것을 알게 된다."
                },
                {
                    "type": "narrative",
                    "location": "가축농장",
                    "character": [
                        "C004"
                    ],
                    "act": "만들다",
                    "emotion": "비장하다",
                    "content": "C004이 동물들을 규합한다."
                },
                {
                    "type": "narrative",
                    "location": "가축농장",
                    "character": [
                        "C003",
                        "C004"
                    ],
                    "act": "때리다",
                    "emotion": "단호하다",
                    "content": "동물들은 힘을 합쳐 C003 일당을 쓰러뜨린다."
                },
                {
                    "type": "narrative",
                    "location": "가축농장",
                    "character": [
                        "C003",
                        "C004"
                    ],
                    "act": "간다/이동한다",
                    "emotion": "무섭다",
                    "content": "C003와 C001들을 기세를 못 이기고 도망쳐 버린다."
                },
                {
                    "type": "narrative",
                    "location": "C011의 집 외부",
                    "character": [
                        "C004"
                    ],
                    "act": "포박하다/체포하다",
                    "emotion": "허무하다",
                    "content": "부서진 C011의 집 밖으로 C004과 그를 따르는 동물들의 모습이 한동안 보인다."
                }
            ]
        }
    ]
}