{
    "country": "02",
    "class_1": "08",
    "내용분류": {
        "감정": [
            "해당없음"
        ],
        "대화형태": [
            "설명"
        ],
        "행동": [
            "해당없음"
        ],
        "인물관계": [
            "부모와자식"
        ],
        "캐릭터": [
            "요괴",
            "서생",
            "동물"
        ],
        "직업/신분": [
            "해당없음"
        ],
        "장르": [
            "판타지"
        ],
        "사건/모티프": [
            "해당없음"
        ],
        "공간": [
            "자연"
        ]
    },
    "주제어": [
        "물고기",
        "지느러미",
        "왕사수",
        "노란 옷",
        "팔"
    ],
    "주제문": "배 위에 물고기 지느러미 한 조각이 발견되었고, 이는 왕사수가 잘라낸 사람의 팔임을 깨달은 순간이었다."
}